{"wiztable": {"2022.10.08": [["coffee", 1665243300.0, "checked"], ["vitamins", 1665212940.0, ""], ["log", 0, ""], ["news", 0, ""], ["ritual", 0, ""], ["weight", 0, ""], ["pushup1", 0, ""], ["shower", 0, ""], ["lotion", 0, ""], ["teeth", 0, ""], ["pushup2", 0, ""], ["nextnutri", 0, ""], ["calsync", 0, ""], ["promises", 0, ""], ["passedfixed", 0, ""], ["passedrepeat", 0, ""], ["priority", 0, ""], ["milestones", 0, ""], ["decisions", 0, ""], ["schedfits", 0, ""], ["variable", 0, ""], ["realistic", 0, ""], ["backup", 0, ""], ["pushup3", 0, ""], ["daynutri", 0, ""]], "2022.10.07": [["coffee", 1665153000.0, "checked"], ["vitamins", 0, ""], ["log", 0, ""], ["news", 0, ""], ["ritual", 0, ""], ["weight", 0, ""], ["pushup1", 0, ""], ["shower", 0, ""], ["lotion", 0, ""], ["teeth", 0, ""], ["pushup2", 0, ""], ["nextnutri", 0, ""], ["calsync", 0, ""], ["promises", 0, ""], ["passedfixed", 0, ""], ["passedrepeat", 0, ""], ["priority", 0, ""], ["milestones", 0, ""], ["decisions", 0, ""], ["schedfits", 0, ""], ["variable", 0, ""], ["realistic", 0, ""], ["backup", 0, ""], ["pushup3", 0, ""], ["daynutri", 0, ""]], "2022.10.09": [["coffee", 1665328560.0, "checked"], ["vitamins", 1665330060.0, "checked"], ["log", 1665328560.0, "checked"], ["news", 1665330060.0, "checked"], ["ritual", 1665328560.0, "checked"], ["weight", 0, ""], ["pushup1", 0, ""], ["shower", 1665328620.0, "checked"], ["lotion", 0, ""], ["teeth", 1665328620.0, ""], ["neoprene", 0, ""], ["pushup2", 0, ""], ["emailparsed", 0, ""], ["emailresp", 0, ""], ["nextnutri", 0, ""], ["calsync", 1665371580.0, "checked"], ["promises", 1665330300.0, "checked"], ["passedfixed", 1665371520.0, "checked"], ["passedrepeat", 1665371520.0, "checked"], ["priority", 0, ""], ["milestones", 0, ""], ["decisions", 0, ""], ["schedfits", 1665371640.0, "checked"], ["variable", 1665371640.0, "checked"], ["realistic", 1665371640.0, "checked"], ["backup", 1665371700.0, "checked"], ["pushup3", 0, ""], ["acctcomplete", 0, ""], ["armodafinil", 0, ""], ["alcohol", 0, ""], ["daynutri", 1665298800.0, "checked"]], "2022.10.10": [["coffee", 1665407760.0, "checked"], ["vitamins", 1665410460.0, "checked"], ["log", 1665408000.0, "checked"], ["news", 0, ""], ["ritual", 1665414480.0, "checked"], ["weight", 0, ""], ["pushup1", 1665418140.0, "checked"], ["shower", 1665419400.0, "checked"], ["lotion", 0, ""], ["teeth", 1665419400.0, "checked"], ["pushup2", 0, ""], ["emailparsed", 0, ""], ["emailresp", 0, ""], ["nextnutri", 0, ""], ["calsync", 1665392040.0, "checked"], ["promises", 0, ""], ["passedfixed", 1665392520.0, "checked"], ["passedrepeat", 1665392760.0, "checked"], ["priority", 0, ""], ["milestones", 0, ""], ["decisions", 0, ""], ["schedfits", 1665392760.0, "checked"], ["variable", 1665392760.0, "checked"], ["realistic", 1665392760.0, "checked"], ["backup", 1665392820.0, "checked"], ["pushup3", 0, ""], ["acctcomplete", 0, ""], ["armodafinil", 0, ""], ["alcohol", 0, ""], ["daynutri", 1665421860.0, "checked"]], "2022.10.11": [["coffee", 1665508320.0, "checked"], ["vitamins", 1665516360.0, "checked"], ["log", 1665508320.0, "checked"], ["news", 0, ""], ["ritual", 1665524280.0, "checked"], ["weight", 1665506880.0, "232"], ["pushup1", 1665532740.0, "checked"], ["shower", 1665508380.0, "checked"], ["lotion", 1665508380.0, "checked"], ["teeth", 1665532980.0, "checked"], ["pushup2", 0, ""], ["emailparsed", 1665526860.0, "239"], ["emailresp", 1665527100.0, "15"], ["nextnutri", 0, ""], ["calsync", 1665544740.0, "checked"], ["promises", 0, ""], ["passedfixed", 1665544740.0, "checked"], ["passedrepeat", 1665544740.0, "checked"], ["priority", 0, ""], ["milestones", 0, ""], ["decisions", 0, ""], ["schedfits", 1665544740.0, "checked"], ["variable", 1665544800.0, "checked"], ["realistic", 1665544800.0, "checked"], ["backup", 1665544800.0, "checked"], ["pushup3", 0, ""], ["acctcomplete", 1665533040.0, "checked"], ["armodafinil", 1665523080.0, "150"], ["alcohol", 1665524460.0, "24"], ["daynutri", 1665551580.0, "checked"]], "2022.10.12": [["coffee", 1665577740.0, "checked"], ["vitamins", 1665578040.0, "checked"], ["log", 1665577740.0, "checked"], ["news", 1665579240.0, "checked"], ["ritual", 1665579420.0, "checked"], ["weight", 1665577920.0, "233"], ["pushup1", 1665579600.0, "checked"], ["shower", 1665616380.0, "checked"], ["lotion", 1665616380.0, "checked"], ["teeth", 1665616380.0, "checked"], ["pushup2", 1665588540.0, "checked"], ["emailparsed", 1665578160.0, "81"], ["emailresp", 0, ""], ["nextnutri", 0, ""], ["calsync", 1665565260.0, "checked"], ["promises", 1665570240.0, "checked"], ["passedfixed", 1665566700.0, "checked"], ["passedrepeat", 1665570300.0, "checked"], ["priority", 1665570360.0, "checked"], ["milestones", 1665575640.0, "checked"], ["decisions", 1665576240.0, "checked"], ["schedfits", 1665576240.0, "checked"], ["variable", 1665576240.0, "checked"], ["realistic", 1665576240.0, "checked"], ["backup", 1665576300.0, "checked"], ["pushup3", 0, ""], ["acctcomplete", 0, ""], ["armodafinil", 1665588600.0, "75"], ["alcohol", 1665616440.0, "48"], ["daynutri", 1665565260.0, "checked"]], "2022.10.13": [["coffee", 1665651120.0, "checked"], ["vitamins", 1665651960.0, "checked"], ["log", 1665651120.0, "checked"], ["news", 0, ""], ["ritual", 1665653040.0, "checked"], ["weight", 1665652080.0, "234"], ["pushup1", 1665700560.0, "checked"], ["shower", 1665704280.0, "checked"], ["lotion", 1665704280.0, "checked"], ["teeth", 1665704280.0, "checked"], ["neoprene", 0, ""], ["pushup2", 0, ""], ["emailparsed", 1665717840.0, "57"], ["emailresp", 1665697260.0, "2"], ["nextnutri", 0, ""], ["calsync", 1665716100.0, "checked"], ["promises", 1665716160.0, "checked"], ["passedfixed", 1665716160.0, "checked"], ["passedrepeat", 1665716220.0, "checked"], ["priority", 1665716220.0, "checked"], ["milestones", 1665716280.0, "checked"], ["decisions", 1665717480.0, "checked"], ["schedfits", 1665717660.0, "checked"], ["variable", 1665717660.0, "checked"], ["realistic", 1665717660.0, "checked"], ["backup", 1665717720.0, "checked"], ["pushup3", 0, ""], ["acctcomplete", 0, ""], ["armodafinil", 1665700620.0, "140"], ["alcohol", 1665700620.0, "48"], ["daynutri", 1665717720.0, "checked"]], "2022.10.14": [["coffee", 1665754500.0, "checked"], ["vitamins", 1665755940.0, "checked"], ["log", 1665754500.0, "checked"], ["news", 1665756000.0, "checked"], ["ritual", 1665756780.0, "checked"], ["weight", 1665754740.0, "231"], ["pushup1", 0, ""], ["shower", 1665764700.0, "checked"], ["lotion", 1665764700.0, "checked"], ["teeth", 1665764700.0, "checked"], ["neoprene", 0, ""], ["pushup2", 0, ""], ["emailparsed", 0, ""], ["emailresp", 1665763920.0, "1"], ["nextnutri", 0, ""], ["calsync", 1665735420.0, "checked"], ["promises", 1665735780.0, "checked"], ["passedfixed", 1665735780.0, "checked"], ["passedrepeat", 1665735780.0, "checked"], ["priority", 1665735780.0, "checked"], ["milestones", 0, ""], ["decisions", 0, ""], ["schedfits", 1665735840.0, "checked"], ["variable", 1665735840.0, "checked"], ["realistic", 1665735840.0, "checked"], ["backup", 1665735900.0, "checked"], ["pushup3", 0, ""], ["acctcomplete", 0, ""], ["armodafinil", 1665735900.0, "75"], ["alcohol", 1665735900.0, "48"], ["daynutri", 1665733140.0, "checked"]], "2022.10.15": [["coffee", 1665853380.0, "checked"], ["vitamins", 1665853380.0, "checked"], ["log", 1665853380.0, "checked"], ["news", 0, ""], ["ritual", 1665862140.0, "checked"], ["weight", 1665852900.0, "232"], ["pushup1", 1665863760.0, "checked"], ["shower", 1665866760.0, "checked"], ["lotion", 1665866760.0, "checked"], ["teeth", 1665866760.0, "checked"], ["neoprene", 0, ""], ["pushup2", 1665873120.0, "checked"], ["emailparsed", 0, ""], ["emailresp", 0, ""], ["nextnutri", 0, ""], ["calsync", 1665890760.0, "checked"], ["promises", 0, ""], ["passedfixed", 1665890760.0, "checked"], ["passedrepeat", 1665890760.0, "checked"], ["priority", 1665890760.0, "checked"], ["milestones", 0, ""], ["decisions", 0, ""], ["schedfits", 1665890760.0, "checked"], ["variable", 1665890760.0, "checked"], ["realistic", 1665890820.0, "checked"], ["backup", 1665890820.0, "checked"], ["pushup3", 0, ""], ["acctcomplete", 0, ""], ["armodafinil", 0, ""], ["alcohol", 1665821700.0, "48"], ["daynutri", 1665890820.0, "checked"]], "2022.10.16": [["coffee", 1665908760.0, "checked"], ["vitamins", 1665908580.0, "checked"], ["log", 1665908280.0, "checked"], ["news", 0, ""], ["ritual", 1665915540.0, "checked"], ["weight", 1665908580.0, "233"], ["pushup1", 0, ""], ["shower", 1665939600.0, "checked"], ["lotion", 1665939600.0, "checked"], ["teeth", 1665939600.0, "checked"], ["neoprene", 1665915840.0, "checked"], ["pushup2", 0, ""], ["emailparsed", 0, ""], ["emailresp", 0, ""], ["nextnutri", 0, ""], ["calsync", 1665979800.0, "checked"], ["promises", 1665983880.0, "checked"], ["passedfixed", 1665983880.0, "checked"], ["passedrepeat", 1665983880.0, "checked"], ["priority", 1665983880.0, "checked"], ["milestones", 0, ""], ["decisions", 0, ""], ["schedfits", 1665983880.0, "checked"], ["variable", 1665983880.0, "checked"], ["realistic", 1665983880.0, "checked"], ["backup", 1665983940.0, "checked"], ["pushup3", 0, ""], ["acctcomplete", 0, ""], ["armodafinil", 1665961800.0, "150"], ["alcohol", 1665961740.0, "24"], ["daynutri", 1665983940.0, "checked"]], "2022.10.17": [["coffee", 1666010340.0, "checked"], ["vitamins", 1666016760.0, "checked"], ["log", 1666010400.0, "checked"], ["news", 0, ""], ["ritual", 1666050360.0, "checked"], ["weight", 1666010400.0, "231"], ["pushup1", 0, ""], ["shower", 1666050360.0, "checked"], ["lotion", 1666050360.0, "checked"], ["teeth", 1666050360.0, "checked"], ["neoprene", 0, ""], ["pushup2", 0, ""], ["emailparsed", 0, ""], ["emailresp", 0, ""], ["nextnutri", 0, ""], ["calsync", 1666012740.0, "checked"], ["promises", 1666012800.0, "checked"], ["passedfixed", 1666012800.0, "checked"], ["passedrepeat", 1666012800.0, "checked"], ["priority", 0, ""], ["milestones", 0, ""], ["decisions", 1666013220.0, "checked"], ["schedfits", 1666013340.0, "checked"], ["variable", 1666013340.0, "checked"], ["realistic", 1666013340.0, "checked"], ["backup", 1666013460.0, "checked"], ["pushup3", 0, ""], ["acctcomplete", 0, ""], ["armodafinil", 1666011720.0, "75"], ["alcohol", 1666011720.0, "48"], ["daynutri", 1666011720.0, "checked"]], "2022.10.18": [["coffee", 1666098420.0, "checked"], ["vitamins", 1666100100.0, "checked"], ["log", 1666098420.0, "checked"], ["news", 0, ""], ["ritual", 1666104240.0, "checked"], ["weight", 1666098420.0, "232"], ["pushup1", 0, ""], ["shower", 1666126980.0, "checked"], ["lotion", 1666126980.0, "checked"], ["teeth", 1666126980.0, "checked"], ["neoprene", 0, ""], ["pushup2", 0, ""], ["emailparsed", 1666127040.0, "4"], ["emailresp", 1666127040.0, "1"], ["nextnutri", 0, ""], ["calsync", 1666085400.0, "checked"], ["promises", 0, ""], ["passedfixed", 1666085400.0, "checked"], ["passedrepeat", 1666085400.0, "checked"], ["priority", 0, ""], ["milestones", 0, ""], ["decisions", 0, ""], ["schedfits", 1666085400.0, "checked"], ["variable", 1666085400.0, "checked"], ["realistic", 1666085400.0, "checked"], ["backup", 1666085460.0, "checked"], ["pushup3", 0, ""], ["acctcomplete", 0, ""], ["armodafinil", 1666100100.0, "150"], ["alcohol", 1666078620.0, "48"], ["daynutri", 1666078560.0, "checked"]], "2022.10.19": [["coffee", 1666165200.0, "checked"], ["vitamins", 1666165380.0, "checked"], ["log", 1666165020.0, "checked"], ["news", 0, ""], ["ritual", 1666187280.0, "checked"], ["weight", 1666165440.0, "229"], ["pushup1", 0, ""], ["shower", 1666198140.0, "checked"], ["lotion", 1666198140.0, "checked"], ["teeth", 1666198140.0, "checked"], ["neoprene", 0, ""], ["pushup2", 0, ""], ["emailparsed", 1666187220.0, "2"], ["emailresp", 1666187220.0, "1"], ["nextnutri", 0, ""], ["calsync", 1666171740.0, ""], ["promises", 0, ""], ["passedfixed", 1666171740.0, ""], ["passedrepeat", 1666171740.0, ""], ["priority", 0, ""], ["milestones", 0, ""], ["decisions", 0, ""], ["schedfits", 1666171740.0, ""], ["variable", 1666171740.0, ""], ["realistic", 1666171740.0, ""], ["backup", 0, ""], ["pushup3", 0, ""], ["acctcomplete", 0, ""], ["armodafinil", 0, ""], ["alcohol", 0, ""], ["daynutri", 1666170180.0, "checked"]], "2022.10.20": [["coffee", 1666284780.0, "checked"], ["vitamins", 0, ""], ["log", 1666282980.0, "checked"], ["news", 0, ""], ["ritual", 0, ""], ["weight", 0, ""], ["pushup1", 0, ""], ["shower", 1666256520.0, "checked"], ["lotion", 1666256520.0, "checked"], ["teeth", 1666256520.0, "checked"], ["neoprene", 0, ""], ["pushup2", 0, ""], ["emailparsed", 1666282980.0, "1"], ["emailresp", 0, ""], ["nextnutri", 0, ""], ["calsync", 1666256640.0, "checked"], ["promises", 0, ""], ["passedfixed", 1666256820.0, "checked"], ["passedrepeat", 1666257060.0, "checked"], ["priority", 0, ""], ["milestones", 0, ""], ["decisions", 0, ""], ["schedfits", 1666258260.0, "checked"], ["variable", 1666258320.0, "checked"], ["realistic", 1666258320.0, "checked"], ["backup", 1666258320.0, "checked"], ["pushup3", 0, ""], ["acctcomplete", 0, ""], ["armodafinil", 1666256520.0, "75"], ["alcohol", 1666256520.0, "24"], ["daynutri", 1666256520.0, "checked"]], "2022.10.21": [["coffee", 1666409880.0, "checked"], ["vitamins", 1666409880.0, ""], ["log", 1666409880.0, "checked"], ["news", 0, ""], ["ritual", 0, ""], ["weight", 0, ""], ["pushup1", 0, ""], ["shower", 1666409880.0, "checked"], ["lotion", 1666409880.0, "checked"], ["teeth", 1666409880.0, "checked"], ["neoprene", 0, ""], ["pushup2", 0, ""], ["emailparsed", 0, ""], ["emailresp", 0, ""], ["nextnutri", 0, ""], ["calsync", 1666375080.0, "checked"], ["promises", 0, ""], ["passedfixed", 1666375200.0, "checked"], ["passedrepeat", 1666375320.0, "checked"], ["priority", 0, ""], ["milestones", 0, ""], ["decisions", 0, ""], ["schedfits", 1666376100.0, "checked"], ["variable", 1666375320.0, "checked"], ["realistic", 1666376100.0, "checked"], ["backup", 1666376160.0, "checked"], ["pushup3", 0, ""], ["acctcomplete", 0, ""], ["armodafinil", 1666375140.0, "0"], ["alcohol", 1666375140.0, "24"], ["daynutri", 1666375080.0, "checked"]], "2022.10.22": [["coffee", 1666459980.0, "checked"], ["vitamins", 1666450200.0, "checked"], ["log", 1666459980.0, "checked"], ["news", 0, ""], ["ritual", 1666460220.0, "checked"], ["weight", 1666458840.0, "227.8"], ["pushup1", 0, ""], ["shower", 1666450200.0, "checked"], ["lotion", 1666450200.0, "checked"], ["teeth", 1666450200.0, ""], ["neoprene", 0, ""], ["pushup2", 0, ""], ["emailparsed", 0, ""], ["emailresp", 0, ""], ["nextnutri", 0, ""], ["calsync", 1666450560.0, "checked"], ["promises", 0, ""], ["passedfixed", 1666450620.0, "checked"], ["passedrepeat", 1666450620.0, "checked"], ["priority", 0, ""], ["milestones", 0, ""], ["decisions", 0, ""], ["schedfits", 1666450620.0, "checked"], ["variable", 1666450620.0, "checked"], ["realistic", 1666450620.0, "checked"], ["backup", 1666450620.0, "checked"], ["pushup3", 0, ""], ["acctcomplete", 0, ""], ["armodafinil", 1666450680.0, "75"], ["alcohol", 1666450680.0, "24"], ["daynutri", 1666450620.0, "checked"]], "2022.10.23": [["coffee", 1666534560.0, "checked"], ["vitamins", 1666547940.0, "checked"], ["log", 1666534680.0, "checked"], ["news", 1666536600.0, "checked"], ["ritual", 1666536600.0, "checked"], ["weight", 1666534200.0, "228"], ["pushup1", 0, ""], ["shower", 1666544520.0, "checked"], ["lotion", 1666544520.0, "checked"], ["teeth", 1666544520.0, "checked"], ["neoprene", 0, ""], ["pushup2", 0, ""], ["emailparsed", 1666544520.0, "72"], ["emailresp", 1666548120.0, "3"], ["nextnutri", 0, ""], ["calsync", 1666537440.0, "checked"], ["promises", 0, ""], ["passedfixed", 1666537560.0, "checked"], ["passedrepeat", 1666537560.0, "checked"], ["priority", 0, ""], ["milestones", 0, ""], ["decisions", 0, ""], ["schedfits", 0, ""], ["variable", 1666538100.0, "checked"], ["realistic", 1666538100.0, "checked"], ["backup", 1666538100.0, "checked"], ["pushup3", 0, ""], ["acctcomplete", 0, ""], ["armodafinil", 0, ""], ["alcohol", 1666534320.0, "48"], ["daynutri", 1666534260.0, "checked"]], "2022.10.24": [["coffee", 1666618260.0, "checked"], ["vitamins", 1666624560.0, "checked"], ["log", 1666618260.0, "checked"], ["news", 0, ""], ["ritual", 1666659900.0, "checked"], ["weight", 0, ""], ["pushup1", 1666660020.0, "checked"], ["shower", 1666631520.0, "checked"], ["lotion", 1666631520.0, "checked"], ["teeth", 1666631520.0, "checked"], ["neoprene", 1666660080.0, "checked"], ["pushup2", 0, ""], ["emailparsed", 0, ""], ["emailresp", 1666671000.0, "2"], ["nextnutri", 0, ""], ["calsync", 1666660860.0, "checked"], ["promises", 1666662420.0, "checked"], ["passedfixed", 1666663560.0, "checked"], ["passedrepeat", 1666664100.0, "checked"], ["priority", 1666664100.0, "checked"], ["milestones", 0, ""], ["decisions", 0, ""], ["schedfits", 0, ""], ["variable", 1666664340.0, "checked"], ["realistic", 1666664340.0, "checked"], ["backup", 1666664340.0, "checked"], ["pushup3", 0, ""], ["acctcomplete", 0, ""], ["armodafinil", 0, ""], ["alcohol", 1666664400.0, "72"], ["daynutri", 1666600260.0, "checked"]], "2022.10.25": [["coffee", 1666711620.0, "checked"], ["vitamins", 1666765740.0, "checked"], ["log", 1666711620.0, "checked"], ["news", 0, ""], ["ritual", 1666713180.0, "checked"], ["weight", 1666711620.0, "228"], ["pushup1", 0, ""], ["shower", 1666765740.0, "checked"], ["lotion", 1666765740.0, "checked"], ["teeth", 1666765740.0, "checked"], ["neoprene", 0, ""], ["pushup2", 0, ""], ["emailparsed", 1666763100.0, "36"], ["emailresp", 1666763100.0, "2"], ["nextnutri", 0, ""], ["calsync", 1666765860.0, "checked"], ["promises", 1666765980.0, "checked"], ["passedfixed", 1666766040.0, "checked"], ["passedrepeat", 1666766100.0, "checked"], ["priority", 1666766100.0, "checked"], ["milestones", 0, ""], ["decisions", 0, ""], ["schedfits", 1666766340.0, "checked"], ["variable", 1666766400.0, "checked"], ["realistic", 1666766400.0, "checked"], ["backup", 1666766400.0, "checked"], ["pushup3", 0, ""], ["acctcomplete", 0, ""], ["armodafinil", 1666766460.0, "75"], ["alcohol", 1666766460.0, "48"], ["daynutri", 1666766460.0, "checked"]], "2022.10.26": [["coffee", 1666830780.0, "checked"], ["vitamins", 1666795020.0, "checked"], ["log", 1666789620.0, "checked"], ["news", 0, ""], ["ritual", 1666795020.0, "checked"], ["weight", 0, ""], ["pushup1", 0, ""], ["shower", 1666796820.0, "checked"], ["lotion", 1666796820.0, "checked"], ["teeth", 1666796820.0, "checked"], ["neoprene", 0, ""], ["pushup2", 0, ""], ["emailparsed", 1666801680.0, "5"], ["emailresp", 1666801680.0, "3"], ["nextnutri", 0, ""], ["calsync", 1666830720.0, "checked"], ["promises", 0, ""], ["passedfixed", 1666831680.0, "checked"], ["passedrepeat", 1666831680.0, "checked"], ["priority", 0, ""], ["milestones", 0, ""], ["decisions", 0, ""], ["schedfits", 1666831680.0, "checked"], ["variable", 1666831680.0, "checked"], ["realistic", 1666831680.0, "checked"], ["backup", 0, ""], ["pushup3", 0, ""], ["acctcomplete", 0, ""], ["armodafinil", 1666830780.0, "75"], ["alcohol", 1666830780.0, "48"], ["daynutri", 1666830780.0, "checked"]], "2022.10.27": [["coffee", 1666917240.0, "checked"], ["vitamins", 1666917420.0, "checked"], ["log", 1666917420.0, "checked"], ["news", 0, ""], ["ritual", 0, ""], ["weight", 1666915980.0, "230"], ["pushup1", 0, ""], ["shower", 1666917420.0, "checked"], ["lotion", 1666917420.0, "checked"], ["teeth", 1666917420.0, "checked"], ["neoprene", 0, ""], ["pushup2", 0, ""], ["emailparsed", 1666917480.0, "4"], ["emailresp", 1666917480.0, "2"], ["nextnutri", 0, ""], ["calsync", 1666918020.0, "checked"], ["promises", 0, ""], ["passedfixed", 1666918020.0, "checked"], ["passedrepeat", 1666918020.0, "checked"], ["priority", 0, ""], ["milestones", 0, ""], ["decisions", 0, ""], ["schedfits", 1666918020.0, "checked"], ["variable", 1666918020.0, "checked"], ["realistic", 1666938300.0, "checked"], ["backup", 1666918140.0, "checked"], ["pushup3", 0, ""], ["acctcomplete", 0, ""], ["armodafinil", 1666917480.0, "150"], ["alcohol", 1666917480.0, "24"], ["daynutri", 1666938360.0, "checked"]], "2022.10.28": [["coffee", 1666978860.0, "checked"], ["vitamins", 1666970100.0, "checked"], ["log", 1666978920.0, "checked"], ["news", 0, ""], ["ritual", 1666970100.0, "checked"], ["weight", 1666979460.0, "229"], ["pushup1", 0, ""], ["shower", 1666970100.0, "checked"], ["lotion", 1666970100.0, "checked"], ["teeth", 1666970100.0, "checked"], ["neoprene", 0, ""], ["pushup2", 0, ""], ["emailparsed", 1666970100.0, "3"], ["emailresp", 0, ""], ["nextnutri", 0, ""], ["calsync", 0, ""], ["promises", 0, ""], ["passedfixed", 1666997580.0, "checked"], ["passedrepeat", 1666997760.0, "checked"], ["priority", 0, ""], ["milestones", 0, ""], ["decisions", 0, ""], ["schedfits", 1666997760.0, "checked"], ["variable", 1666997760.0, "checked"], ["realistic", 1666997820.0, "checked"], ["backup", 0, ""], ["pushup3", 0, ""], ["acctcomplete", 0, ""], ["armodafinil", 1666970100.0, "75"], ["alcohol", 1666970100.0, "24"], ["daynutri", 1666970100.0, "checked"]], "2022.10.29": [["coffee", 1667056560.0, "checked"], ["vitamins", 1667057580.0, "checked"], ["log", 1667056560.0, "checked"], ["news", 1667057580.0, "checked"], ["ritual", 1667057400.0, "checked"], ["weight", 1667057640.0, "229"], ["pushup1", 0, ""], ["shower", 1667083800.0, "checked"], ["lotion", 1667083800.0, "checked"], ["teeth", 1667083800.0, "checked"], ["neoprene", 0, ""], ["pushup2", 0, ""], ["emailparsed", 1667083800.0, "3"], ["emailresp", 1667083800.0, "0"], ["nextnutri", 0, ""], ["calsync", 0, ""], ["promises", 0, ""], ["passedfixed", 1667030100.0, "checked"], ["passedrepeat", 1667030160.0, "checked"], ["priority", 0, ""], ["milestones", 0, ""], ["decisions", 0, ""], ["schedfits", 1667032920.0, "checked"], ["variable", 1667032980.0, "checked"], ["realistic", 1667032980.0, "checked"], ["backup", 0, ""], ["pushup3", 0, ""], ["acctcomplete", 0, ""], ["armodafinil", 1667032980.0, "75"], ["alcohol", 1667033040.0, "0"], ["daynutri", 1667033280.0, "checked"]], "2022.10.30": [["coffee", 0, ""], ["vitamins", 0, ""], ["log", 1667119680.0, "checked"], ["news", 0, ""], ["ritual", 0, ""], ["weight", 0, ""], ["pushup1", 0, ""], ["shower", 1667115720.0, "checked"], ["lotion", 0, ""], ["teeth", 1667115720.0, "checked"], ["neoprene", 0, ""], ["pushup2", 0, ""], ["emailparsed", 1667115780.0, "2"], ["emailresp", 1667115780.0, "1"], ["nextnutri", 0, ""], ["calsync", 1667115780.0, "checked"], ["promises", 0, ""], ["passedfixed", 1667116080.0, "checked"], ["passedrepeat", 1667116080.0, "checked"], ["priority", 1667116080.0, ""], ["milestones", 0, ""], ["decisions", 0, ""], ["schedfits", 1667116080.0, "checked"], ["variable", 1667116080.0, "checked"], ["realistic", 1667116140.0, "checked"], ["backup", 1667116140.0, "checked"], ["pushup3", 0, ""], ["acctcomplete", 0, ""], ["armodafinil", 0, ""], ["alcohol", 0, ""], ["daynutri", 1667115660.0, "checked"]], "2022.10.31": [["coffee", 1667201880.0, "checked"], ["vitamins", 0, ""], ["log", 1667201880.0, "checked"], ["news", 1667201880.0, "checked"], ["ritual", 1667201880.0, "checked"], ["weight", 0, ""], ["pushup1", 0, ""], ["shower", 1667211600.0, "checked"], ["lotion", 1667211600.0, "checked"], ["teeth", 1667211600.0, "checked"], ["neoprene", 0, ""], ["pushup2", 0, ""], ["emailparsed", 0, ""], ["emailresp", 0, ""], ["nextnutri", 0, ""], ["calsync", 1667213340.0, "checked"], ["promises", 0, ""], ["passedfixed", 1667213580.0, "checked"], ["passedrepeat", 1667214720.0, "checked"], ["priority", 0, ""], ["milestones", 0, ""], ["decisions", 0, ""], ["schedfits", 1667214720.0, "checked"], ["variable", 1667214780.0, "checked"], ["realistic", 1667216160.0, "checked"], ["backup", 1667216220.0, "checked"], ["pushup3", 0, ""], ["acctcomplete", 0, ""], ["armodafinil", 0, ""], ["alcohol", 0, ""], ["daynutri", 1667211660.0, "checked"]], "2022.11.01": [["coffee", 1667288640.0, "checked"], ["vitamins", 1667302680.0, "checked"], ["log", 1667298060.0, "checked"], ["news", 1667288640.0, "checked"], ["ritual", 1667288640.0, "checked"], ["weight", 0, ""], ["pushup1", 1667298060.0, "checked"], ["shower", 1667298120.0, "checked"], ["lotion", 1667298120.0, "checked"], ["teeth", 1667288640.0, "checked"], ["neoprene", 0, ""], ["pushup2", 1667304120.0, "checked"], ["emailparsed", 1667288640.0, "3"], ["emailresp", 1667288700.0, "2"], ["nextnutri", 0, ""], ["calsync", 1667289420.0, "checked"], ["promises", 0, ""], ["passedfixed", 1667289480.0, "checked"], ["passedrepeat", 1667289480.0, "checked"], ["priority", 0, ""], ["milestones", 0, ""], ["decisions", 0, ""], ["schedfits", 1667290560.0, "checked"], ["variable", 1667290620.0, "checked"], ["realistic", 1667290620.0, "checked"], ["backup", 1667290620.0, "checked"], ["pushup3", 0, ""], ["acctcomplete", 0, ""], ["armodafinil", 1667298180.0, "75"], ["alcohol", 0, ""], ["daynutri", 0, ""]], "2022.11.02": [["coffee", 1667374620.0, "checked"], ["vitamins", 1667374620.0, "checked"], ["log", 1667374620.0, "checked"], ["news", 1667374620.0, "checked"], ["ritual", 1667374620.0, "checked"], ["weight", 0, ""], ["pushup1", 1667374620.0, "checked"], ["shower", 1667374680.0, "checked"], ["lotion", 1667374680.0, "checked"], ["teeth", 1667374680.0, "checked"], ["neoprene", 1667374680.0, "checked"], ["pushup2", 1667374620.0, "checked"], ["emailparsed", 1667378760.0, "44"], ["emailresp", 1667380920.0, "10"], ["nextnutri", 0, ""], ["calsync", 1667382180.0, "checked"], ["promises", 0, ""], ["passedfixed", 1667382240.0, "checked"], ["passedrepeat", 1667382360.0, "checked"], ["priority", 0, ""], ["milestones", 0, ""], ["decisions", 0, ""], ["schedfits", 1667382360.0, "checked"], ["variable", 1667382360.0, "checked"], ["realistic", 1667382360.0, "checked"], ["backup", 1667382360.0, "checked"], ["pushup3", 0, ""], ["acctcomplete", 0, ""], ["armodafinil", 1667375400.0, "140"], ["alcohol", 0, ""], ["daynutri", 1667382120.0, "checked"]], "2022.11.03": [["coffee", 1667468040.0, "checked"], ["vitamins", 1667468040.0, "checked"], ["log", 1667468040.0, "checked"], ["news", 1667468040.0, "checked"], ["ritual", 1667468040.0, "checked"], ["weight", 0, ""], ["pushup1", 1667468040.0, "checked"], ["shower", 1667468100.0, "checked"], ["lotion", 1667468100.0, "checked"], ["teeth", 1667468100.0, "checked"], ["neoprene", 1667468100.0, "checked"], ["pushup2", 1667474700.0, "checked"], ["emailparsed", 1667470800.0, "72"], ["emailresp", 1667470800.0, "8"], ["nextnutri", 0, ""], ["calsync", 1667477220.0, "checked"], ["promises", 0, ""], ["passedfixed", 0, ""], ["passedrepeat", 0, ""], ["priority", 0, ""], ["milestones", 0, ""], ["decisions", 0, ""], ["schedfits", 0, ""], ["variable", 0, ""], ["realistic", 0, ""], ["backup", 1667474700.0, "checked"], ["pushup3", 0, ""], ["acctcomplete", 0, ""], ["armodafinil", 1667468820.0, "80"], ["alcohol", 0, ""], ["daynutri", 1667475060.0, "checked"]], "2022.11.04": [["coffee", 1667559840.0, "checked"], ["vitamins", 1667559840.0, "checked"], ["log", 1667559840.0, "checked"], ["news", 1667559900.0, "checked"], ["ritual", 1667559900.0, "checked"], ["weight", 0, ""], ["pushup1", 1667559900.0, "checked"], ["shower", 1667559960.0, "checked"], ["lotion", 1667559960.0, "checked"], ["teeth", 0, ""], ["neoprene", 1667559960.0, "checked"], ["pushup2", 1667555700.0, "checked"], ["emailparsed", 1667559180.0, "42"], ["emailresp", 1667559180.0, "11"], ["nextnutri", 0, ""], ["calsync", 1667558340.0, "checked"], ["promises", 1667560560.0, "checked"], ["passedfixed", 1667561580.0, "checked"], ["passedrepeat", 1667562480.0, "checked"], ["priority", 1667563680.0, "checked"], ["milestones", 1667566080.0, "checked"], ["decisions", 1667566800.0, ""], ["schedfits", 1667566800.0, "checked"], ["variable", 1667566080.0, "checked"], ["realistic", 1667566800.0, "checked"], ["backup", 1667557380.0, "checked"], ["pushup3", 0, ""], ["acctcomplete", 0, ""], ["armodafinil", 1667555700.0, "75"], ["alcohol", 0, ""], ["daynutri", 1667555700.0, "checked"]], "2022.11.05": [["coffee", 1667642100.0, "checked"], ["vitamins", 1667642100.0, "checked"], ["log", 1667643660.0, "checked"], ["news", 1667642100.0, "checked"], ["ritual", 1667642100.0, "checked"], ["weight", 0, ""], ["pushup1", 1667642100.0, "checked"], ["shower", 1667642100.0, "checked"], ["lotion", 1667642100.0, "checked"], ["teeth", 0, ""], ["neoprene", 1667642100.0, "checked"], ["pushup2", 1667642100.0, "checked"], ["emailparsed", 0, ""], ["emailresp", 0, ""], ["nextnutri", 0, ""], ["calsync", 1667635800.0, "checked"], ["promises", 1667635800.0, "checked"], ["passedfixed", 1667635980.0, "checked"], ["passedrepeat", 1667637060.0, "checked"], ["priority", 1667637060.0, "checked"], ["milestones", 1667637060.0, "checked"], ["decisions", 0, ""], ["schedfits", 1667637420.0, "checked"], ["variable", 1667637060.0, "checked"], ["realistic", 1667637420.0, "checked"], ["backup", 1667637600.0, "checked"], ["pushup3", 0, ""], ["acctcomplete", 0, ""], ["armodafinil", 1667642100.0, "75"], ["alcohol", 0, ""], ["daynutri", 1667635740.0, "checked"]], "2022.11.06": [["coffee", 1667721960.0, "checked"], ["vitamins", 1667721960.0, "checked"], ["log", 1667721960.0, "checked"], ["news", 1667721960.0, "checked"], ["ritual", 1667721960.0, "checked"], ["weight", 0, ""], ["pushup1", 1667721960.0, "checked"], ["shower", 1667721960.0, "checked"], ["lotion", 1667721960.0, "checked"], ["teeth", 0, ""], ["neoprene", 1667721960.0, "checked"], ["pushup2", 1667721960.0, "checked"], ["emailparsed", 1667722920.0, "6"], ["emailresp", 1667722920.0, "2"], ["nextnutri", 0, ""], ["calsync", 1667722920.0, "checked"], ["promises", 1667722920.0, "checked"], ["passedfixed", 1667723040.0, "checked"], ["passedrepeat", 1667723040.0, "checked"], ["priority", 1667723040.0, "checked"], ["milestones", 1667723040.0, "checked"], ["decisions", 0, ""], ["schedfits", 1667723460.0, "checked"], ["variable", 1667723040.0, "checked"], ["realistic", 1667723460.0, "checked"], ["backup", 1667723460.0, "checked"], ["pushup3", 1667756880.0, "checked"], ["acctcomplete", 0, ""], ["armodafinil", 1667722140.0, "75"], ["alcohol", 0, ""], ["daynutri", 0, ""]], "2022.11.07": [["coffee", 1667812500.0, "checked"], ["vitamins", 1667812500.0, "checked"], ["log", 1667812500.0, "checked"], ["news", 1667812500.0, "checked"], ["ritual", 1667812500.0, "checked"], ["weight", 0, ""], ["pushup1", 1667812500.0, "checked"], ["shower", 1667812500.0, "checked"], ["lotion", 1667812500.0, "checked"], ["teeth", 1667812500.0, ""], ["neoprene", 1667812560.0, "checked"], ["pushup2", 1667810640.0, "checked"], ["emailparsed", 1667811600.0, "5"], ["emailresp", 1667811600.0, "4"], ["nextnutri", 0, ""], ["calsync", 1667811300.0, "checked"], ["promises", 1667811360.0, "checked"], ["passedfixed", 1667811420.0, "checked"], ["passedrepeat", 1667811480.0, "checked"], ["priority", 1667811540.0, "checked"], ["milestones", 1667811540.0, "checked"], ["decisions", 0, ""], ["schedfits", 1667811780.0, "checked"], ["variable", 1667811480.0, "checked"], ["realistic", 1667811780.0, "checked"], ["backup", 1667811900.0, "checked"], ["pushup3", 1667810640.0, "checked"], ["acctcomplete", 0, ""], ["armodafinil", 1667810640.0, "150"], ["alcohol", 0, ""], ["daynutri", 1667810640.0, "checked"]], "2022.11.08": [["coffee", 1667896500.0, "checked"], ["vitamins", 0, ""], ["log", 1667896500.0, "checked"], ["news", 1667897040.0, "checked"], ["ritual", 1667897040.0, "checked"], ["weight", 0, ""], ["pushup1", 1667897040.0, "checked"], ["shower", 1667897100.0, "checked"], ["lotion", 1667897100.0, "checked"], ["teeth", 0, ""], ["neoprene", 0, ""], ["pushup2", 1667897460.0, "checked"], ["emailparsed", 1667898300.0, "44"], ["emailresp", 1667898300.0, "5"], ["nextnutri", 0, ""], ["calsync", 1667897880.0, "checked"], ["promises", 1667897880.0, "checked"], ["passedfixed", 1667897880.0, "checked"], ["passedrepeat", 1667898300.0, "checked"], ["priority", 1667898300.0, "checked"], ["milestones", 0, ""], ["decisions", 0, ""], ["schedfits", 1667898300.0, "checked"], ["variable", 1667898300.0, "checked"], ["realistic", 1667898300.0, "checked"], ["backup", 1667898360.0, "checked"], ["pushup3", 0, ""], ["acctcomplete", 0, ""], ["armodafinil", 1667898360.0, "0"], ["alcohol", 0, ""], ["daynutri", 1667898360.0, "checked"]], "2022.11.09": [["coffee", 1667983620.0, "checked"], ["vitamins", 1667983680.0, "checked"], ["log", 1667983680.0, "checked"], ["news", 1667983680.0, "checked"], ["ritual", 1667983680.0, "checked"], ["weight", 0, ""], ["pushup1", 1667983680.0, "checked"], ["shower", 1667983680.0, "checked"], ["lotion", 1667983680.0, "checked"], ["teeth", 0, ""], ["neoprene", 0, ""], ["pushup2", 1667988480.0, "checked"], ["emailparsed", 1667984100.0, "23"], ["emailresp", 1667984100.0, "1"], ["nextnutri", 0, ""], ["calsync", 1667988540.0, "checked"], ["promises", 0, ""], ["passedfixed", 1667988600.0, "checked"], ["passedrepeat", 1667988600.0, "checked"], ["priority", 0, ""], ["milestones", 0, ""], ["decisions", 0, ""], ["schedfits", 1667988840.0, "checked"], ["variable", 1667988600.0, "checked"], ["realistic", 1667988840.0, "checked"], ["backup", 1667988900.0, "checked"], ["pushup3", 0, ""], ["acctcomplete", 0, ""], ["armodafinil", 1667984820.0, "75"], ["alcohol", 1667988660.0, "5"], ["daynutri", 1667988480.0, "checked"]], "2022.11.10": [["coffee", 1668074520.0, "checked"], ["vitamins", 0, ""], ["log", 1668074520.0, "checked"], ["news", 1668074520.0, "checked"], ["ritual", 1668074520.0, "checked"], ["weight", 0, ""], ["pushup1", 1668074520.0, "checked"], ["shower", 1668074520.0, "checked"], ["lotion", 1668074520.0, "checked"], ["teeth", 0, ""], ["neoprene", 0, ""], ["pushup2", 1668078840.0, "checked"], ["emailparsed", 1668077880.0, "47"], ["emailresp", 1668078000.0, "7"], ["nextnutri", 0, ""], ["calsync", 0, ""], ["promises", 0, ""], ["passedfixed", 0, ""], ["passedrepeat", 0, ""], ["priority", 0, ""], ["milestones", 0, ""], ["decisions", 0, ""], ["schedfits", 0, ""], ["variable", 0, ""], ["realistic", 0, ""], ["backup", 0, ""], ["pushup3", 0, ""], ["acctcomplete", 0, ""], ["armodafinil", 0, ""], ["alcohol", 0, ""], ["daynutri", 1668078960.0, "checked"]], "2022.11.12": [["coffee", 1668251100.0, "checked"], ["vitamins", 0, ""], ["log", 1668251100.0, "checked"], ["news", 1668251100.0, "checked"], ["ritual", 1668251100.0, "checked"], ["weight", 0, ""], ["pushup1", 1668251100.0, "checked"], ["shower", 1668251100.0, "checked"], ["lotion", 1668251100.0, "checked"], ["teeth", 0, ""], ["neoprene", 0, ""], ["pushup2", 1668251820.0, "checked"], ["emailparsed", 1668251160.0, "2"], ["emailresp", 1668251160.0, "2"], ["nextnutri", 0, ""], ["calsync", 1668252840.0, "checked"], ["promises", 0, ""], ["passedfixed", 1668252900.0, "checked"], ["passedrepeat", 1668252900.0, "checked"], ["priority", 0, ""], ["milestones", 0, ""], ["decisions", 0, ""], ["schedfits", 1668252900.0, "checked"], ["variable", 1668252900.0, "checked"], ["realistic", 1668252900.0, "checked"], ["backup", 0, ""], ["pushup3", 0, ""], ["acctcomplete", 0, ""], ["armodafinil", 1668251880.0, "75"], ["alcohol", 0, ""], ["daynutri", 1668252180.0, "checked"]], "2022.11.11": [["coffee", 1668165180.0, "checked"], ["vitamins", 0, ""], ["log", 0, ""], ["news", 0, ""], ["ritual", 0, ""], ["weight", 0, ""], ["pushup1", 1668165180.0, "checked"], ["shower", 1668165180.0, "checked"], ["lotion", 1668165180.0, "checked"], ["teeth", 0, ""], ["neoprene", 0, ""], ["pushup2", 0, ""], ["emailparsed", 0, ""], ["emailresp", 0, ""], ["nextnutri", 0, ""], ["calsync", 1668165480.0, "checked"], ["promises", 0, ""], ["passedfixed", 1668165660.0, "checked"], ["passedrepeat", 1668165720.0, "checked"], ["priority", 0, ""], ["milestones", 0, ""], ["decisions", 0, ""], ["schedfits", 1668166080.0, "checked"], ["variable", 1668165720.0, "checked"], ["realistic", 1668166080.0, "checked"], ["backup", 1668166140.0, "checked"], ["pushup3", 0, ""], ["acctcomplete", 0, ""], ["armodafinil", 1668165180.0, "75"], ["alcohol", 0, ""], ["daynutri", 1668165180.0, "checked"]], "2022.11.13": [["coffee", 1668338100.0, "checked"], ["vitamins", 1668339420.0, "checked"], ["log", 1668338100.0, "checked"], ["news", 1668341520.0, "checked"], ["ritual", 1668338100.0, "checked"], ["weight", 0, ""], ["pushup1", 1668338100.0, "checked"], ["shower", 1668338100.0, "checked"], ["lotion", 1668338100.0, "checked"], ["teeth", 0, ""], ["neoprene", 0, ""], ["pushup2", 1668357660.0, "checked"], ["emailparsed", 1668357660.0, "2"], ["emailresp", 1668357660.0, "2"], ["nextnutri", 0, ""], ["calsync", 1668357780.0, "checked"], ["promises", 0, ""], ["passedfixed", 1668357840.0, "checked"], ["passedrepeat", 1668358020.0, "checked"], ["priority", 0, ""], ["milestones", 0, ""], ["decisions", 0, ""], ["schedfits", 1668358380.0, "checked"], ["variable", 1668358020.0, "checked"], ["realistic", 1668358380.0, "checked"], ["backup", 0, ""], ["pushup3", 0, ""], ["acctcomplete", 0, ""], ["armodafinil", 0, ""], ["alcohol", 0, ""], ["daynutri", 1668357660.0, "checked"]], "2022.11.14": [["coffee", 0, ""], ["vitamins", 1668443760.0, "checked"], ["log", 1668443760.0, "checked"], ["news", 1668417900.0, "checked"], ["ritual", 0, ""], ["weight", 0, ""], ["pushup1", 1668443760.0, "checked"], ["shower", 1668443760.0, "checked"], ["lotion", 1668443760.0, "checked"], ["teeth", 0, ""], ["neoprene", 0, ""], ["pushup2", 0, ""], ["emailparsed", 1668445440.0, "11"], ["emailresp", 0, ""], ["nextnutri", 0, ""], ["calsync", 1668418080.0, "checked"], ["promises", 0, ""], ["passedfixed", 1668418140.0, "checked"], ["passedrepeat", 1668418260.0, "checked"], ["priority", 0, ""], ["milestones", 0, ""], ["decisions", 0, ""], ["schedfits", 1668418320.0, "checked"], ["variable", 1668418260.0, "checked"], ["realistic", 1668418620.0, "checked"], ["backup", 1668418680.0, "checked"], ["pushup3", 0, ""], ["acctcomplete", 0, ""], ["armodafinil", 0, ""], ["alcohol", 1668417480.0, "10"], ["daynutri", 1668417420.0, "checked"]], "2022.11.15": [["coffee", 1668530580.0, "checked"], ["vitamins", 0, ""], ["log", 1668530580.0, "checked"], ["news", 1668530580.0, "checked"], ["ritual", 1668530580.0, "checked"], ["weight", 0, ""], ["pushup1", 1668530640.0, "checked"], ["shower", 1668503640.0, "checked"], ["lotion", 1668530580.0, "checked"], ["teeth", 0, ""], ["neoprene", 1668530640.0, "checked"], ["pushup2", 0, ""], ["emailparsed", 1668530580.0, "28"], ["emailresp", 1668530580.0, "3"], ["nextnutri", 0, ""], ["calsync", 1668514680.0, "checked"], ["promises", 0, ""], ["passedfixed", 1668514680.0, "checked"], ["passedrepeat", 1668514740.0, "checked"], ["priority", 0, ""], ["milestones", 0, ""], ["decisions", 0, ""], ["schedfits", 1668514740.0, "checked"], ["variable", 1668514740.0, "checked"], ["realistic", 1668514860.0, "checked"], ["backup", 1668514920.0, "checked"], ["pushup3", 0, ""], ["acctcomplete", 0, ""], ["armodafinil", 0, ""], ["alcohol", 0, ""], ["daynutri", 1668514740.0, "checked"]], "2022.11.16": [["coffee", 1668600180.0, "checked"], ["vitamins", 0, ""], ["log", 1668600180.0, "checked"], ["news", 1668600180.0, "checked"], ["ritual", 1668600180.0, "checked"], ["weight", 0, ""], ["pushup1", 1668600180.0, "checked"], ["shower", 1668600240.0, "checked"], ["lotion", 1668600240.0, "checked"], ["teeth", 0, ""], ["neoprene", 1668652320.0, ""], ["pushup2", 1668652320.0, "checked"], ["emailparsed", 1668652320.0, "2"], ["emailresp", 1668652320.0, "2"], ["nextnutri", 0, ""], ["calsync", 1668652380.0, "checked"], ["promises", 0, ""], ["passedfixed", 1668652440.0, "checked"], ["passedrepeat", 1668652680.0, "checked"], ["priority", 0, ""], ["milestones", 0, ""], ["decisions", 0, ""], ["schedfits", 1668652920.0, "checked"], ["variable", 1668652680.0, "checked"], ["realistic", 1668652920.0, "checked"], ["backup", 1668652980.0, "checked"], ["pushup3", 0, ""], ["acctcomplete", 0, ""], ["armodafinil", 1668652380.0, "75"], ["alcohol", 0, ""], ["daynutri", 1668652320.0, "checked"]], "2022.11.17": [["coffee", 1668737820.0, "checked"], ["vitamins", 1668738480.0, "checked"], ["log", 1668738480.0, "checked"], ["news", 1668738480.0, "checked"], ["ritual", 1668738480.0, "checked"], ["weight", 0, ""], ["pushup1", 0, ""], ["shower", 1668738480.0, "checked"], ["lotion", 1668738480.0, "checked"], ["teeth", 0, ""], ["neoprene", 0, ""], ["pushup2", 0, ""], ["emailparsed", 1668726600.0, "2"], ["emailresp", 1668726600.0, "1"], ["nextnutri", 0, ""], ["calsync", 1668726600.0, "checked"], ["promises", 0, ""], ["passedfixed", 1668726660.0, "checked"], ["passedrepeat", 1668726660.0, "checked"], ["priority", 0, ""], ["milestones", 0, ""], ["decisions", 0, ""], ["schedfits", 1668727080.0, "checked"], ["variable", 1668726660.0, "checked"], ["realistic", 1668727080.0, "checked"], ["backup", 1668727140.0, "checked"], ["pushup3", 0, ""], ["acctcomplete", 0, ""], ["armodafinil", 1668738780.0, "75"], ["alcohol", 1668726540.0, "20"], ["daynutri", 0, ""]], "2022.11.18": [["coffee", 1668812820.0, "checked"], ["vitamins", 1668812820.0, "checked"], ["log", 1668812820.0, "checked"], ["news", 1668812820.0, "checked"], ["ritual", 1668812820.0, "checked"], ["weight", 0, ""], ["pushup1", 0, ""], ["shower", 1668825120.0, "checked"], ["lotion", 1668825120.0, "checked"], ["teeth", 1668825120.0, "checked"], ["neoprene", 0, ""], ["pushup2", 0, ""], ["emailparsed", 0, ""], ["emailresp", 0, ""], ["nextnutri", 0, ""], ["calsync", 1668781200.0, "checked"], ["promises", 0, ""], ["passedfixed", 1668783480.0, "checked"], ["passedrepeat", 1668783480.0, "checked"], ["priority", 0, ""], ["milestones", 0, ""], ["decisions", 0, ""], ["schedfits", 1668783840.0, "checked"], ["variable", 1668783480.0, "checked"], ["realistic", 1668783840.0, "checked"], ["backup", 1668784020.0, "checked"], ["pushup3", 0, ""], ["acctcomplete", 0, ""], ["armodafinil", 0, ""], ["alcohol", 1668812820.0, "20"], ["daynutri", 1668784020.0, "checked"]], "2022.11.19": [["coffee", 1668866940.0, "checked"], ["vitamins", 1668917040.0, "checked"], ["log", 1668866940.0, "checked"], ["news", 1668917040.0, "checked"], ["ritual", 0, ""], ["weight", 1668866940.0, "224"], ["pushup1", 1668866940.0, "checked"], ["shower", 1668917040.0, "checked"], ["lotion", 1668917040.0, "checked"], ["teeth", 1668917040.0, ""], ["neoprene", 1668917040.0, "checked"], ["pushup2", 1668917040.0, ""], ["emailparsed", 1668917100.0, "70"], ["emailresp", 1668917100.0, "2"], ["nextnutri", 0, ""], ["calsync", 1668859020.0, "checked"], ["promises", 0, ""], ["passedfixed", 1668859020.0, "checked"], ["passedrepeat", 1668859020.0, "checked"], ["priority", 0, ""], ["milestones", 0, ""], ["decisions", 0, ""], ["schedfits", 1668859020.0, "checked"], ["variable", 1668859020.0, "checked"], ["realistic", 1668859020.0, "checked"], ["backup", 1668859020.0, "checked"], ["pushup3", 0, ""], ["acctcomplete", 0, ""], ["armodafinil", 0, ""], ["alcohol", 1668927780.0, "30"], ["daynutri", 1668859020.0, "checked"]], "2022.11.20": [["coffee", 1668978240.0, "checked"], ["vitamins", 1668945420.0, "checked"], ["log", 1668978240.0, "checked"], ["news", 1668978240.0, "checked"], ["ritual", 1668978240.0, "checked"], ["weight", 1668966720.0, "225"], ["pushup1", 0, ""], ["shower", 1668945480.0, "checked"], ["lotion", 1668945480.0, "checked"], ["teeth", 0, ""], ["neoprene", 0, ""], ["pushup2", 0, ""], ["emailparsed", 1668978180.0, "19"], ["emailresp", 1668978240.0, "6"], ["nextnutri", 0, ""], ["calsync", 1668950760.0, "checked"], ["promises", 1668950880.0, "checked"], ["passedfixed", 1668951120.0, "checked"], ["passedrepeat", 1668951120.0, "checked"], ["priority", 1668951120.0, ""], ["milestones", 0, ""], ["decisions", 0, ""], ["schedfits", 1668951660.0, "checked"], ["variable", 1668951120.0, "checked"], ["realistic", 1668951660.0, "checked"], ["backup", 1668951660.0, "checked"], ["pushup3", 0, ""], ["acctcomplete", 0, ""], ["armodafinil", 0, ""], ["alcohol", 1668945360.0, "30"], ["daynutri", 1668945360.0, "checked"]], "2022.11.21": [["coffee", 1669031880.0, "checked"], ["vitamins", 1669032900.0, "checked"], ["log", 1669032780.0, "checked"], ["news", 1669036860.0, "checked"], ["ritual", 1669033440.0, "checked"], ["weight", 1669031880.0, "226"], ["pushup1", 1669052760.0, "checked"], ["shower", 1669048620.0, "checked"], ["lotion", 1669048620.0, "checked"], ["teeth", 1669048620.0, "checked"], ["neoprene", 0, ""], ["pushup2", 0, ""], ["emailparsed", 1669033500.0, "48"], ["emailresp", 1669034400.0, "1"], ["nextnutri", 0, ""], ["calsync", 1669048680.0, "checked"], ["promises", 1669048680.0, "checked"], ["passedfixed", 1669048860.0, "checked"], ["passedrepeat", 0, ""], ["priority", 0, ""], ["milestones", 0, ""], ["decisions", 0, ""], ["schedfits", 0, ""], ["variable", 1669048860.0, "checked"], ["realistic", 1669048920.0, "checked"], ["backup", 0, ""], ["pushup3", 0, ""], ["acctcomplete", 0, ""], ["armodafinil", 1669048920.0, "60"], ["alcohol", 1669048920.0, "40"], ["daynutri", 1669048920.0, "checked"]], "2022.11.22": [["coffee", 1669134180.0, "checked"], ["vitamins", 1669138740.0, "checked"], ["log", 1669134180.0, "checked"], ["news", 1669138740.0, "checked"], ["ritual", 1669140900.0, "checked"], ["weight", 1669133940.0, "225"], ["pushup1", 0, ""], ["shower", 1669140900.0, "checked"], ["lotion", 1669140900.0, "checked"], ["teeth", 1669141740.0, "checked"], ["neoprene", 0, ""], ["pushup2", 0, ""], ["emailparsed", 1669141740.0, "4"], ["emailresp", 1669141740.0, "3"], ["nextnutri", 0, ""], ["calsync", 0, ""], ["promises", 0, ""], ["passedfixed", 0, ""], ["passedrepeat", 0, ""], ["priority", 0, ""], ["milestones", 0, ""], ["decisions", 0, ""], ["schedfits", 0, ""], ["variable", 0, ""], ["realistic", 0, ""], ["backup", 0, ""], ["pushup3", 0, ""], ["acctcomplete", 0, ""], ["armodafinil", 0, ""], ["alcohol", 1669162860.0, "10"], ["daynutri", 1669162920.0, "checked"]], "2022.11.29": [["coffee", 1669757640.0, "checked"], ["vitamins", 1669766520.0, "checked"], ["log", 1669766460.0, "checked"], ["news", 1669766580.0, "checked"], ["ritual", 1669766580.0, "checked"], ["weight", 0, ""], ["pushup1", 0, ""], ["shower", 1669757640.0, "checked"], ["lotion", 1669757700.0, "checked"], ["teeth", 1669757700.0, ""], ["neoprene", 0, ""], ["pushup2", 0, ""], ["emailparsed", 0, ""], ["emailresp", 0, ""], ["nextnutri", 0, ""], ["calsync", 1669768140.0, "checked"], ["promises", 1669768200.0, "checked"], ["passedfixed", 1669768680.0, "checked"], ["passedrepeat", 1669769040.0, "checked"], ["priority", 0, ""], ["milestones", 0, ""], ["decisions", 0, ""], ["schedfits", 1669769940.0, "checked"], ["variable", 1669769100.0, "checked"], ["realistic", 1669769340.0, "checked"], ["backup", 1669769400.0, "checked"], ["pushup3", 0, ""], ["acctcomplete", 0, ""], ["armodafinil", 0, ""], ["alcohol", 1669766580.0, "10"], ["daynutri", 1669794960.0, "checked"]], "2022.11.28": [["coffee", 0, ""], ["vitamins", 0, ""], ["log", 0, ""], ["news", 0, ""], ["ritual", 0, ""], ["weight", 0, ""], ["pushup1", 0, ""], ["shower", 1669680240.0, "checked"], ["lotion", 1669680240.0, "checked"], ["teeth", 1669680240.0, "checked"], ["neoprene", 0, ""], ["pushup2", 0, ""], ["emailparsed", 0, ""], ["emailresp", 0, ""], ["nextnutri", 0, ""], ["calsync", 0, ""], ["promises", 0, ""], ["passedfixed", 0, ""], ["passedrepeat", 0, ""], ["priority", 0, ""], ["milestones", 0, ""], ["decisions", 0, ""], ["schedfits", 0, ""], ["variable", 0, ""], ["realistic", 0, ""], ["backup", 0, ""], ["pushup3", 0, ""], ["acctcomplete", 0, ""], ["armodafinil", 1669680300.0, "225"], ["alcohol", 1669680300.0, "20"], ["daynutri", 1669680480.0, "checked"]], "2022.11.27": [["coffee", 1669594080.0, "checked"], ["vitamins", 1669594080.0, "checked"], ["log", 0, ""], ["news", 0, ""], ["ritual", 1669594140.0, "checked"], ["weight", 0, ""], ["pushup1", 0, ""], ["shower", 1669594140.0, "checked"], ["lotion", 1669594140.0, "checked"], ["teeth", 0, ""], ["neoprene", 0, ""], ["pushup2", 0, ""], ["emailparsed", 0, ""], ["emailresp", 0, ""], ["nextnutri", 0, ""], ["calsync", 0, ""], ["promises", 0, ""], ["passedfixed", 0, ""], ["passedrepeat", 0, ""], ["priority", 0, ""], ["milestones", 0, ""], ["decisions", 0, ""], ["schedfits", 0, ""], ["variable", 0, ""], ["realistic", 0, ""], ["backup", 0, ""], ["pushup3", 0, ""], ["acctcomplete", 0, ""], ["armodafinil", 1669594140.0, "150"], ["alcohol", 0, ""], ["daynutri", 1669594980.0, "checked"]], "2022.11.26": [["coffee", 1669507800.0, "checked"], ["vitamins", 1669507800.0, "checked"], ["log", 0, ""], ["news", 1669507800.0, "checked"], ["ritual", 1669507800.0, "checked"], ["weight", 0, ""], ["pushup1", 0, ""], ["shower", 1669507800.0, "checked"], ["lotion", 0, ""], ["teeth", 0, ""], ["neoprene", 0, ""], ["pushup2", 0, ""], ["emailparsed", 0, ""], ["emailresp", 0, ""], ["nextnutri", 0, ""], ["calsync", 0, ""], ["promises", 0, ""], ["passedfixed", 0, ""], ["passedrepeat", 0, ""], ["priority", 0, ""], ["milestones", 0, ""], ["decisions", 0, ""], ["schedfits", 0, ""], ["variable", 0, ""], ["realistic", 0, ""], ["backup", 0, ""], ["pushup3", 0, ""], ["acctcomplete", 0, ""], ["armodafinil", 1669507800.0, "75"], ["alcohol", 0, ""], ["daynutri", 0, ""]], "2022.11.25": [["coffee", 1669421460.0, "checked"], ["vitamins", 1669421460.0, "checked"], ["log", 0, ""], ["news", 1669421460.0, "checked"], ["ritual", 0, ""], ["weight", 0, ""], ["pushup1", 0, ""], ["shower", 1669421460.0, "checked"], ["lotion", 0, ""], ["teeth", 0, ""], ["neoprene", 0, ""], ["pushup2", 0, ""], ["emailparsed", 0, ""], ["emailresp", 0, ""], ["nextnutri", 0, ""], ["calsync", 0, ""], ["promises", 0, ""], ["passedfixed", 0, ""], ["passedrepeat", 0, ""], ["priority", 0, ""], ["milestones", 0, ""], ["decisions", 0, ""], ["schedfits", 0, ""], ["variable", 0, ""], ["realistic", 0, ""], ["backup", 0, ""], ["pushup3", 0, ""], ["acctcomplete", 0, ""], ["armodafinil", 0, ""], ["alcohol", 1669421460.0, "30"], ["daynutri", 0, ""]], "2022.11.24": [["coffee", 1669335120.0, "checked"], ["vitamins", 1669335120.0, "checked"], ["log", 1669335120.0, ""], ["news", 1669335120.0, "checked"], ["ritual", 0, ""], ["weight", 0, ""], ["pushup1", 0, ""], ["shower", 1669335120.0, "checked"], ["lotion", 0, ""], ["teeth", 0, ""], ["neoprene", 0, ""], ["pushup2", 0, ""], ["emailparsed", 0, ""], ["emailresp", 0, ""], ["nextnutri", 0, ""], ["calsync", 0, ""], ["promises", 0, ""], ["passedfixed", 0, ""], ["passedrepeat", 0, ""], ["priority", 0, ""], ["milestones", 0, ""], ["decisions", 0, ""], ["schedfits", 0, ""], ["variable", 0, ""], ["realistic", 0, ""], ["backup", 0, ""], ["pushup3", 0, ""], ["acctcomplete", 0, ""], ["armodafinil", 0, ""], ["alcohol", 1669335120.0, "30"], ["daynutri", 1669335540.0, "checked"]], "2022.11.23": [["coffee", 1669249140.0, "checked"], ["vitamins", 1669249140.0, "checked"], ["log", 0, ""], ["news", 1669249200.0, "checked"], ["ritual", 0, ""], ["weight", 0, ""], ["pushup1", 0, ""], ["shower", 1669249200.0, "checked"], ["lotion", 0, ""], ["teeth", 0, ""], ["neoprene", 0, ""], ["pushup2", 0, ""], ["emailparsed", 0, ""], ["emailresp", 0, ""], ["nextnutri", 0, ""], ["calsync", 0, ""], ["promises", 0, ""], ["passedfixed", 0, ""], ["passedrepeat", 0, ""], ["priority", 0, ""], ["milestones", 0, ""], ["decisions", 0, ""], ["schedfits", 0, ""], ["variable", 0, ""], ["realistic", 0, ""], ["backup", 0, ""], ["pushup3", 0, ""], ["acctcomplete", 0, ""], ["armodafinil", 0, ""], ["alcohol", 1669249200.0, "20"], ["daynutri", 1669249260.0, "checked"]], "2022.11.30": [["coffee", 1669835820.0, "checked"], ["vitamins", 1669864980.0, "checked"], ["log", 1669835820.0, "checked"], ["news", 0, ""], ["ritual", 1669864980.0, "checked"], ["weight", 1669835820.0, "225"], ["pushup1", 1669818480.0, "checked"], ["shower", 1669835820.0, "checked"], ["lotion", 1669835820.0, "checked"], ["teeth", 0, ""], ["neoprene", 0, ""], ["pushup2", 0, ""], ["emailparsed", 1669818480.0, "3"], ["emailresp", 1669818540.0, "2"], ["nextnutri", 0, ""], ["calsync", 1669819440.0, "checked"], ["promises", 1669819440.0, "checked"], ["passedfixed", 1669819440.0, "checked"], ["passedrepeat", 1669819560.0, "checked"], ["priority", 1669819800.0, "checked"], ["milestones", 0, ""], ["decisions", 0, ""], ["schedfits", 1669819800.0, "checked"], ["variable", 1669819560.0, "checked"], ["realistic", 1669819800.0, "checked"], ["backup", 1669819860.0, "checked"], ["pushup3", 0, ""], ["acctcomplete", 0, ""], ["armodafinil", 0, ""], ["alcohol", 1669835820.0, "30"], ["daynutri", 1669819860.0, "checked"]], "2022.12.01": [["coffee", 1669904820.0, "checked"], ["vitamins", 1669906380.0, "checked"], ["log", 1669904820.0, "checked"], ["news", 1669906320.0, "checked"], ["ritual", 1669906680.0, "checked"], ["weight", 0, ""], ["pushup1", 1669962540.0, "checked"], ["shower", 1669963440.0, "checked"], ["lotion", 1669963440.0, "checked"], ["teeth", 0, ""], ["neoprene", 0, ""], ["pushup2", 1669962540.0, "checked"], ["emailparsed", 0, ""], ["emailresp", 0, ""], ["nextnutri", 0, ""], ["calsync", 1669916940.0, "checked"], ["promises", 1669916940.0, "checked"], ["passedfixed", 1669917000.0, "checked"], ["passedrepeat", 1669917180.0, "checked"], ["priority", 0, ""], ["milestones", 0, ""], ["decisions", 0, ""], ["schedfits", 1669917240.0, "checked"], ["variable", 1669917240.0, "checked"], ["realistic", 1669917240.0, "checked"], ["backup", 1669917240.0, "checked"], ["pushup3", 0, ""], ["acctcomplete", 0, ""], ["armodafinil", 0, ""], ["alcohol", 1669962540.0, "30"], ["daynutri", 1669917240.0, "checked"]], "2022.12.02": [["coffee", 1670003220.0, "checked"], ["vitamins", 1670008260.0, "checked"], ["log", 1670003220.0, "checked"], ["news", 0, ""], ["ritual", 1670008260.0, "checked"], ["weight", 1670003220.0, "223.4"], ["pushup1", 1670003280.0, "checked"], ["shower", 1669974540.0, "checked"], ["lotion", 1669974540.0, "checked"], ["teeth", 1669974540.0, "checked"], ["neoprene", 0, ""], ["pushup2", 0, ""], ["emailparsed", 0, ""], ["emailresp", 0, ""], ["nextnutri", 0, ""], ["calsync", 1669974780.0, "checked"], ["promises", 0, ""], ["passedfixed", 1669974840.0, "checked"], ["passedrepeat", 1669974840.0, "checked"], ["priority", 0, ""], ["milestones", 0, ""], ["decisions", 0, ""], ["schedfits", 1669975020.0, "checked"], ["variable", 1669974840.0, "checked"], ["realistic", 1669975080.0, "checked"], ["backup", 0, ""], ["pushup3", 0, ""], ["acctcomplete", 0, ""], ["armodafinil", 0, ""], ["alcohol", 1669974600.0, "20"], ["daynutri", 1669974600.0, "checked"]], "2022.12.03": [["coffee", 1670091840.0, "checked"], ["vitamins", 0, ""], ["log", 1670091840.0, "checked"], ["news", 0, ""], ["ritual", 0, ""], ["weight", 0, ""], ["pushup1", 0, ""], ["shower", 1670091840.0, "checked"], ["lotion", 1670091840.0, "checked"], ["teeth", 0, ""], ["neoprene", 0, ""], ["pushup2", 0, ""], ["emailparsed", 0, ""], ["emailresp", 0, ""], ["nextnutri", 0, ""], ["calsync", 1670072880.0, "checked"], ["promises", 0, ""], ["passedfixed", 1670073000.0, "checked"], ["passedrepeat", 1670073060.0, "checked"], ["priority", 0, ""], ["milestones", 0, ""], ["decisions", 0, ""], ["schedfits", 1670073060.0, "checked"], ["variable", 1670073060.0, "checked"], ["realistic", 1670073060.0, "checked"], ["backup", 1670073060.0, "checked"], ["pushup3", 0, ""], ["acctcomplete", 0, ""], ["armodafinil", 0, ""], ["alcohol", 1670073060.0, "25"], ["daynutri", 1670073120.0, "checked"]], "2022.12.04": [["coffee", 1670143320.0, "checked"], ["vitamins", 1670159040.0, "checked"], ["log", 1670151600.0, "checked"], ["news", 0, ""], ["ritual", 1670156880.0, "checked"], ["weight", 0, ""], ["pushup1", 0, ""], ["shower", 1670176140.0, "checked"], ["lotion", 1670176140.0, "checked"], ["teeth", 1670176140.0, "checked"], ["neoprene", 0, ""], ["pushup2", 0, ""], ["emailparsed", 1670147760.0, "2"], ["emailresp", 1670147760.0, "2"], ["nextnutri", 0, ""], ["calsync", 1670147760.0, "checked"], ["promises", 0, ""], ["passedfixed", 1670147820.0, "checked"], ["passedrepeat", 1670147820.0, "checked"], ["priority", 0, ""], ["milestones", 0, ""], ["decisions", 0, ""], ["schedfits", 1670148000.0, "checked"], ["variable", 1670147820.0, "checked"], ["realistic", 1670148060.0, "checked"], ["backup", 0, ""], ["pushup3", 0, ""], ["acctcomplete", 0, ""], ["armodafinil", 1670141220.0, "75"], ["alcohol", 1670143260.0, "30"], ["daynutri", 1670148060.0, "checked"]], "2022.12.05": [["coffee", 1670262120.0, "checked"], ["vitamins", 1670296980.0, "checked"], ["log", 1670234160.0, "checked"], ["news", 1670296980.0, "checked"], ["ritual", 1670296980.0, "checked"], ["weight", 0, ""], ["pushup1", 1670306820.0, "checked"], ["shower", 1670295180.0, "checked"], ["lotion", 1670295180.0, "checked"], ["teeth", 1670295180.0, "checked"], ["neoprene", 0, ""], ["pushup2", 0, ""], ["emailparsed", 0, ""], ["emailresp", 0, ""], ["nextnutri", 0, ""], ["calsync", 1670295180.0, "checked"], ["promises", 0, ""], ["passedfixed", 0, ""], ["passedrepeat", 0, ""], ["priority", 0, ""], ["milestones", 0, ""], ["decisions", 0, ""], ["schedfits", 0, ""], ["variable", 0, ""], ["realistic", 0, ""], ["backup", 0, ""], ["pushup3", 0, ""], ["acctcomplete", 0, ""], ["armodafinil", 1670295180.0, "75"], ["alcohol", 1670295180.0, "20"], ["daynutri", 1670295180.0, "checked"]], "2022.12.06": [["coffee", 1670381340.0, "checked"], ["vitamins", 1670381520.0, "checked"], ["log", 1670381520.0, "checked"], ["news", 0, ""], ["ritual", 1670381520.0, "checked"], ["weight", 0, ""], ["pushup1", 0, ""], ["shower", 0, ""], ["lotion", 0, ""], ["teeth", 0, ""], ["neoprene", 0, ""], ["pushup2", 0, ""], ["emailparsed", 0, ""], ["emailresp", 0, ""], ["nextnutri", 0, ""], ["calsync", 1670382600.0, "checked"], ["promises", 0, ""], ["passedfixed", 1670383140.0, "checked"], ["passedrepeat", 1670383140.0, "checked"], ["priority", 0, ""], ["milestones", 0, ""], ["decisions", 0, ""], ["schedfits", 0, ""], ["variable", 1670383140.0, "checked"], ["realistic", 1670383140.0, "checked"], ["backup", 1670383200.0, "checked"], ["pushup3", 0, ""], ["acctcomplete", 0, ""], ["armodafinil", 0, ""], ["alcohol", 1670393220.0, "20"], ["daynutri", 1670378760.0, "checked"]], "2022.12.07": [["coffee", 1670465160.0, "checked"], ["vitamins", 1670465160.0, "checked"], ["log", 1670465160.0, "checked"], ["news", 1670466780.0, "checked"], ["ritual", 0, ""], ["weight", 0, ""], ["pushup1", 0, ""], ["shower", 1670465160.0, "checked"], ["lotion", 1670465160.0, "checked"], ["teeth", 1670465160.0, "checked"], ["neoprene", 0, ""], ["pushup2", 0, ""], ["emailparsed", 1670466780.0, "2"], ["emailresp", 1670466780.0, "2"], ["nextnutri", 0, ""], ["calsync", 1670467380.0, "checked"], ["promises", 0, ""], ["passedfixed", 1670467380.0, "checked"], ["passedrepeat", 0, ""], ["priority", 0, ""], ["milestones", 0, ""], ["decisions", 0, ""], ["schedfits", 1670467380.0, "checked"], ["variable", 1670467380.0, "checked"], ["realistic", 1670467380.0, "checked"], ["backup", 1670467380.0, "checked"], ["pushup3", 0, ""], ["acctcomplete", 0, ""], ["armodafinil", 1670465100.0, "75"], ["alcohol", 1670465160.0, "35"], ["daynutri", 0, ""]], "2022.12.08": [["coffee", 1670542500.0, "checked"], ["vitamins", 1670542560.0, "checked"], ["log", 1670542560.0, "checked"], ["news", 1670542560.0, "checked"], ["ritual", 1670542980.0, "checked"], ["weight", 1670542980.0, "225"], ["pushup1", 0, ""], ["shower", 0, ""], ["lotion", 0, ""], ["teeth", 0, ""], ["neoprene", 0, ""], ["pushup2", 0, ""], ["emailparsed", 0, ""], ["emailresp", 0, ""], ["nextnutri", 0, ""], ["calsync", 1670543220.0, "checked"], ["promises", 0, ""], ["passedfixed", 1670543400.0, "checked"], ["passedrepeat", 1670543400.0, "checked"], ["priority", 0, ""], ["milestones", 0, ""], ["decisions", 0, ""], ["schedfits", 1670543400.0, "checked"], ["variable", 1670543400.0, "checked"], ["realistic", 1670543400.0, "checked"], ["backup", 0, ""], ["pushup3", 0, ""], ["acctcomplete", 0, ""], ["armodafinil", 0, ""], ["alcohol", 0, ""], ["daynutri", 0, ""]]}, "nutrition": {"2022.10.08": [], "2022.10.07": [], "2022.10.09": [[1665305242.8232203, "camembert", 4.0], [1665328936.020338, "seaweed", 1.0], [1665357166.823194, "knackebrot", 3.0], [1665357185.7871807, "Peanuts", 1.0], [1665357213.2367795, "Tuna", 2.0], [1665357230.735015, "Vodka", 1.0], [1665371198.4015775, "hamburger", 1.0], [1665380229.0653422, "avocado", 0.25], [1665407759.6039553, "rice cake", 3.0]], "2022.10.10": [[1665410512.9218426, "peanuts", 2.0], [1665425124.8988976, "protein bar", 1.0], [1665432298.1528614, "yogurt", 1.0], [1665432315.6772966, "tomato grape", 15.0], [1665432337.9706712, "rockstar recovery", 1.0], [1665448147.2551808, "rice cake", 1.0], [1665451107.985859, "seaweed", 1.0], [1665461842.3860586, "orzo salad", 1.25], [1665461854.5460906, "feta olive mix", 1.0], [1665478245.8816128, "whiskey", 1.0]], "2022.10.11": [[1665511983.4265244, "rice cake", 2.0], [1665512003.500439, "yogurt", 2.0], [1665512271.9430206, "turkey", 4.0], [1665512291.7239645, "mac and cheese", 1.0], [1665516396.6294127, "orange", 1.0], [1665544038.659882, "chili", 1.0], [1665577645.4438019, "cheddar", 4.0], [1665577660.0187304, "knackebrot", 2.0]], "2022.10.12": [[1665577764.9678102, "rice cake", 6.0], [1665603761.4989583, "blue cheese", 1.0], [1665603775.9862227, "knackebrot", 2.0], [1665616460.7788458, "gummi bears", 15.0], [1665626829.1408901, "tomato grape", 15.0], [1665626849.698224, "peanuts", 1.5], [1665626881.0833397, "rockstar recovery", 1.0], [1665629389.4748762, "sushi", 15.0], [1665651240.7693942, "seaweed", 1.0], [1665651287.1045127, "blueberries", 0.75], [1665651373.5743887, "vodka", 1.0], [1665651551.8528693, "pudding", 1.0]], "2022.10.13": [[1665668141.5178514, "peanuts", 3.0], [1665700669.2403955, "vodka", 2.0], [1665700686.0274172, "orzo salad", 1.0], [1665700733.8407865, "yogurt", 1.0], [1665700759.9587545, "cheddar", 4.0], [1665700789.372153, "candybar", 1.0], [1665700855.7236464, "rockstar recovery", 1.0], [1665715878.6822166, "baked vegetable snack", 0.5]], "2022.10.14": [[1665764722.434053, "seaweed", 1.0], [1665768165.0070603, "blueberries", 1.0], [1665784522.5736074, "cheddar", 5.0], [1665784534.484665, "knackebrot", 5.0], [1665784566.7135093, "baked vegetable snack", 0.5], [1665784652.7450442, "raisins", 30.0], [1665795582.1594386, "rice cake", 7.0], [1665822419.1106505, "tomato grape", 30.0], [1665822446.0609155, "candybar", 1.0]], "2022.10.15": [[1665860016.8968725, "peanuts", 4.0], [1665860033.474241, "palak paneer", 1.0], [1665874368.8898058, "seaweed", 1.0], [1665887846.0189946, "orange", 1.0], [1665888706.216456, "baked vegetable snack", 3.0], [1665908182.4970415, "blue cheese", 2.0], [1665908200.2276385, "knackebrot", 2.0]], "2022.10.16": [[1665915643.5013475, "blue cheese", 3.0], [1665931239.906155, "hashbrown", 1.0], [1665931289.4360974, "sausage and egg breakfast sandwich", 1.0], [1665942781.4993062, "seaweed", 1.0], [1665961728.7611108, "rice cake", 3.0], [1665961744.1167684, "tuna", 1.0], [1665961756.3706176, "knackebrot", 2.0], [1665979068.4252565, "orowheat bread", 4.0], [1665979088.622631, "palak paneer", 1.0]], "2022.10.17": [[1666016849.096514, "protein bar", 1.0], [1666016858.9564352, "seaweed", 1.0], [1666039374.6479716, "cheddar", 5.0], [1666039384.3059425, "knackebrot", 5.0], [1666050350.8933723, "gummi bears", 10.0], [1666050484.456459, "canned peaches", 1.0], [1666058827.5445461, "mac and cheese", 1.0]], "2022.10.18": [[1666100274.00017, "apple sauce", 6.0], [1666100294.517812, "peanuts", 5.0], [1666126954.4039097, "rockstar recovery", 1.0], [1666126981.8152046, "seaweed", 1.0], [1666126996.948248, "raisins", 40.0], [1666146116.8382077, "sushi", 10.0]], "2022.10.19": [[1666171887.7402983, "peanuts", 4.0], [1666171896.291234, "raisins", 40.0], [1666222493.6140678, "potato salad", 10.0], [1666222514.1525228, "seaweed", 1.0], [1666222529.8855288, "blueberries", 0.75], [1666234688.419816, "orzo salad", 1.0]], "2022.10.20": [[1666252034.827787, "peanuts", 2.0], [1666342777.8530774, "cheddar", 6.0], [1666342793.155095, "knackebrot", 5.0], [1666342845.5687668, "broccoli cheddar bowl", 1.0], [1666342859.0087187, "banana", 1.0], [1666342874.4585636, "seaweed", 1.0], [1666342898.6140034, "protein bar", 3.0]], "2022.10.21": [[1666396774.827651, "rice cake", 14.0], [1666396790.973743, "banana", 1.0], [1666396802.4725397, "mac and cheese", 1.0], [1666400818.134267, "tuna", 3.0], [1666459133.3497837, "candybar", 1.0]], "2022.10.22": [[1666459062.3488524, "seaweed", 1.0], [1666459113.0020378, "seaweed", 2.0], [1666464944.9886584, "knackebrot", 4.0], [1666464957.3677108, "blue cheese", 3.1], [1666475377.810625, "gummi bears", 50.0], [1666492348.7626324, "peanuts", 1.0], [1666492368.8333063, "candybar", 1.0], [1666492376.4127104, "yogurt", 1.0]], "2022.10.23": [[1666534575.47115, "cereal with milk", 1.0], [1666534585.886794, "yogurt", 2.0], [1666542853.219062, "sausage and egg breakfast sandwich", 1.0], [1666542883.9637873, "hashbrown", 1.0], [1666553838.0595016, "blue cheese", 3.0], [1666553849.3385308, "knackebrot", 4.0], [1666620558.9047801, "seaweed", 3.0], [1666620576.6775768, "rice cake", 7.0], [1666620596.9154117, "blueberries", 0.5], [1666620612.0419147, "peanuts", 2.0], [1666620634.4598088, "orange", 1.0], [1666620663.8925118, "vodka", 1.0]], "2022.10.24": [[1666659818.9017549, "palak paneer", 1.0], [1666659829.8883505, "candybar", 1.0], [1666659837.7628288, "peanuts", 2.0], [1666659849.424566, "vodka", 1.0], [1666659872.8497682, "rockstar recovery", 1.0], [1666659886.6612747, "orzo salad", 1.0]], "2022.10.25": [[1666687699.7589445, "canned peaches", 1.0], [1666687711.582341, "banana", 1.0], [1666711255.1351857, "yogurt", 2.0], [1666711275.4590707, "peanuts", 2.0], [1666731004.3876486, "palak paneer", 1.0], [1666748558.0287843, "sushi", 10.0], [1666766458.6724968, "vodka", 2.0]], "2022.10.26": [[1666789611.0964959, "peanuts", 1.0], [1666793581.5754888, "sausage and egg breakfast sandwich", 1.2], [1666793596.4106045, "hashbrown", 1.0], [1666835135.2853758, "candybar", 1.0], [1666835143.1358438, "banana", 1.0], [1666835159.8755488, "gummi bears", 20.0], [1666839240.4368043, "tuna", 3.3], [1666841831.197616, "blue cheese", 3.0], [1666841845.1084893, "knackebrot", 4.0]], "2022.10.27": [[1666917525.1889162, "feta olive mix", 1.0], [1666917563.1809826, "yogurt", 2.0], [1666917575.0396395, "candybar", 1.0], [1666917691.9295766, "banana", 1.0], [1666917707.2077196, "rockstar recovery", 1.0], [1666923299.373868, "broccoli cheddar bowl", 1.0], [1666938376.1835847, "protein bar", 1.0], [1666938385.5828733, "seaweed", 1.0]], "2022.10.28": [[1666978424.5103135, "yogurt", 2.0], [1666978436.511734, "knackebrot", 6.0], [1666978450.1103077, "peanut butter", 1.5], [1666978479.4150429, "tuna", 1.0], [1666996586.7158067, "orzo salad", 1.0], [1666996594.7634645, "banana", 1.0], [1667056147.2696953, "gummi bears", 11.0], [1667056185.810526, "potato salad", 10.0], [1667056238.877249, "seaweed", 3.0]], "2022.10.29": [[1667083867.2884505, "sausage and egg breakfast sandwich", 1.5], [1667119487.9929004, "mac and cheese", 1.0], [1667119510.9917397, "sourdough bread", 2.0], [1667119525.1836936, "cheddar", 1.0], [1667119550.1563733, "butter", 1.0], [1667119668.791119, "morning pastry", 1.0], [1667119679.6946952, "gummi bears", 25.0]], "2022.10.30": [[1667116324.9092913, "gummi bears", 30.0], [1667202089.1227431, "sausage and egg breakfast sandwich", 1.0]], "2022.10.31": [[1667202059.750069, "stroopwafel", 3.0], [1667297945.7367628, "candybar", 1.0], [1667297974.0966718, "sausage and egg breakfast sandwich", 1.0], [1667298035.249645, "palak paneer", 1.5]], "2022.11.01": [[1667298150.389846, "stroopwafel", 2.0], [1667298158.2561831, "candybar", 2.0], [1667375196.0200295, "cheese cake", 1.0], [1667375408.5239048, "tofu egg salad sandwich", 1.0]], "2022.11.02": [[1667374718.6374238, "dried figs", 1.0], [1667374873.5037644, "grapes", 30.0], [1667375052.9960318, "bell pepper", 1.0], [1667468273.314702, "tofu miso soup with noodles", 1.5], [1667468403.0219, "apfel kuchen", 1.0], [1667468471.2268345, "apple", 1.0], [1667468551.829438, "cola", 2.0]], "2022.11.03": [[1667468071.166078, "stroopwafel", 2.0], [1667468077.8187234, "bell pepper", 1.0], [1667468093.7728043, "dried figs", 2.0], [1667476272.3888955, "whole rye german breads", 2.0], [1667476282.9584327, "cheddar", 2.0], [1667561267.0143857, "vegetarian burrito", 1.0], [1667561425.7355783, "vegan white chocolate", 16.0], [1667561490.8012617, "cola", 1.0]], "2022.11.04": [[1667559926.799806, "apfel kuchen", 1.0], [1667559945.1498523, "dried figs", 2.0], [1667559956.6710188, "grapes", 20.0], [1667641209.5156949, "dried figs", 2.0], [1667641220.4229643, "gummi bears", 40.0], [1667642043.6090138, "doner kebab burrito", 1.75]], "2022.11.05": [[1667641171.7248425, "bell pepper", 1.0], [1667641180.673985, "dried figs", 4.0], [1667641187.9605353, "muesli", 1.0], [1667670800.380214, "vegan white chocolate", 50.0], [1667671001.533951, "jagermeister", 1.0], [1667671016.5419836, "grapes", 15.0], [1667671155.3452506, "gouda", 2.16]], "2022.11.06": [[1667721986.3882635, "apfel kuchen", 1.0], [1667729895.3257692, "muesli", 1.0], [1667754586.8499207, "dried figs", 2.0], [1667756735.2963197, "gouda", 2.16], [1667756764.8581953, "bell pepper", 1.5], [1667756782.156508, "white chocolate", 1.0]], "2022.11.07": [[1667812793.2206876, "dried figs", 2.0], [1667812802.4773877, "panini bread", 1.0], [1667812820.037146, "provolone", 2.0], [1667812867.3844614, "tomato grape", 5.0], [1667896132.2954495, "gummi bears", 80.0], [1667896283.4349942, "orange juice", 1.0], [1667896431.590906, "tiramisu", 1.0], [1667896440.755287, "spinach ravioli", 1.5]], "2022.11.08": [[1667896479.887618, "muesli", 1.0], [1667898369.30669, "bell pepper", 0.75], [1667983776.5935962, "doner kebab burrito", 1.2], [1667983819.891526, "gummi bears", 50.0], [1667983839.5218298, "cola", 1.0], [1667983857.0245728, "dried figs", 1.0]], "2022.11.09": [[1667983736.4130847, "gummi bears", 50.0], [1668074749.7235012, "falafel kebab", 1.5], [1668074790.5066774, "white chocolate", 2.0], [1668074869.2924135, "grapes", 20.0], [1668074900.4119327, "jagermeister", 1.0]], "2022.11.10": [[1668074589.7290049, "muesli", 1.0], [1668074598.472568, "grapes", 10.0], [1668074618.0460248, "gummi bears", 4.0], [1668251693.6866791, "doner kebab burrito", 1.75], [1668251708.828629, "gummi bears", 40.0], [1668251758.4350815, "dried figs", 6.0]], "2022.11.12": [[1668338325.5622442, "white chocolate", 3.775], [1668338361.7082367, "candybar", 1.0], [1668338456.9971633, "mentos", 0.38], [1668338501.7486525, "gummi bears", 67.0], [1668338545.3374822, "gouda", 1.25]], "2022.11.11": [[1668251438.910453, "marzipan", 7.0], [1668251453.0357997, "tuna", 3.0], [1668251482.5044026, "gummi bears", 5.0], [1668251513.8142335, "white chocolate", 2.0], [1668251584.3384843, "hamburger", 1.0], [1668251592.6218836, "cheddar", 1.0]], "2022.11.13": [[1668338168.0420332, "panini bread", 1.0], [1668338201.5416327, "provolone", 2.0], [1668338217.1239307, "tomato grape", 3.0], [1668444051.821797, "cookies", 2.0]], "2022.11.14": [[1668443836.8641634, "grapes", 30.0], [1668443858.4695811, "gouda", 1.25], [1668443899.6300592, "white chocolate", 7.0], [1668503671.1539047, "doner kebab burrito", 1.0], [1668503685.2613719, "gummi bears", 20.0], [1668503810.4178715, "chips", 0.6]], "2022.11.15": [[1668530688.1900392, "panini bread", 1.0], [1668530697.8049123, "tomato grape", 10.0], [1668530712.0835152, "egg", 1.0], [1668530730.204386, "grapes", 30.0], [1668530740.0874698, "white chocolate", 3.5], [1668600285.7032614, "chips", 3.0]], "2022.11.16": [[1668600236.6922398, "gummi bears", 10.0], [1668600246.6094077, "rice cake", 3.0], [1668738671.3249168, "vegetarian burrito", 1.0], [1668738681.2111142, "chips", 2.0], [1668738706.7761574, "gummi bears", 30.0]], "2022.11.17": [[1668738607.018126, "broccoli cheddar bowl", 3.0], [1668738616.418474, "white chocolate", 3.0], [1668812972.844125, "whiskey", 1.0]], "2022.11.18": [[1668812856.022433, "chips", 1.0], [1668812876.8992183, "white chocolate", 2.2], [1668812904.3265083, "gummi bears", 10.0], [1668812928.9906247, "marzipan", 4.0], [1668866995.2760797, "yogurt", 2.0], [1668867006.3847258, "seaweed", 3.0], [1668867024.7836852, "grapes", 20.0]], "2022.11.19": [[1668870552.9044273, "banana chips", 2.0], [1668927693.3918803, "grapes", 20.0], [1668927729.3515303, "feta olive mix", 1.0], [1668927797.2304044, "protein bar", 1.0], [1668927829.5107677, "vodka", 3.0], [1668927870.124058, "knackebrot", 2.0], [1668927877.3726692, "cheddar", 5.0], [1668927923.454782, "tuna", 2.0]], "2022.11.20": [[1669031527.0824409, "sushi", 10.0], [1669031548.2932422, "gouda", 2.0], [1669031664.0562937, "seaweed", 1.0], [1669031685.3585274, "white chocolate", 1.4], [1669031716.13552, "banana", 1.0], [1669031754.9721756, "cereal with milk", 1.0], [1669031776.7360985, "vodka", 3.0]], "2022.11.21": [[1669044020.1670632, "sausage and egg breakfast sandwich", 0.85], [1669044812.1214488, "seaweed", 1.0], [1669047680.0993073, "pecans", 2.0], [1669062234.4402938, "orzo salad", 0.75], [1669092149.5995882, "rice cake", 7.0], [1669092168.3510242, "palak paneer", 1.0], [1669092181.4918892, "grapes", 40.0]], "2022.11.22": [[1669141775.8178134, "banana", 1.0], [1669141783.740912, "cereal with milk", 1.0], [1669767716.9108834, "hamburger", 1.5], [1669767727.0651033, "sausage and egg breakfast sandwich", 1.0], [1669767738.7373729, "white chocolate", 2.0]], "2022.11.29": [[1669760013.854272, "seaweed", 1.0], [1669766615.2059724, "protein bar", 1.0], [1669766628.3108604, "chips", 2.0], [1669766640.5432327, "grapes", 20.0], [1669766657.0739043, "vodka", 1.0], [1669766909.0524716, "banana", 0], [1669784276.6140385, "chili", 1.0], [1669786234.7671025, "tuna", 3.3]], "2022.11.28": [[1669766756.7906609, "whiskey", 2.0], [1669766794.9392817, "hamburger", 2.0], [1669766814.204911, "sausage and egg breakfast sandwich", 1.0], [1669766875.2709825, "banana", 1.0]], "2022.11.27": [[1669767776.4989169, "hamburger", 2.0], [1669767784.359984, "sausage and egg breakfast sandwich", 1.0], [1669767798.5035987, "cola", 1.0]], "2022.11.26": [], "2022.11.25": [[1669767119.2890458, "whiskey", 3.0]], "2022.11.24": [[1669767163.1897206, "whiskey", 3.0], [1669767515.62903, "turkey", 2.0], [1669767531.0622551, "cranberry sauce", 1.0], [1669767538.6042583, "yams", 1.0], [1669767548.8012547, "pumpkin pie", 2.0]], "2022.11.23": [[1669767628.204022, "hamburger", 1.5], [1669767664.8173711, "broccoli cheddar bowl", 1.0], [1669767671.4891138, "whiskey", 2.0]], "2022.11.30": [[1669835857.830023, "grapes", 45.0], [1669849584.8854563, "provolone", 4.0], [1669849595.635492, "knackebrot", 4.0], [1669849620.8505552, "feta olive mix", 1.0], [1669849637.4525723, "vodka", 3.0], [1669864974.4991598, "cheddar", 5.0], [1669865000.451155, "yogurt", 2.0]], "2022.12.01": [[1669904847.3323426, "cheddar", 5.0], [1669908121.6176817, "seaweed", 1.0], [1669957777.2233152, "egg", 4.0], [1669957788.0263758, "mac and cheese", 1.0], [1669957799.6805758, "peanuts", 2.0], [1669957817.6376476, "canned peaches", 1.0], [1669962562.57104, "vodka", 3.0]], "2022.12.02": [[1670003696.7371097, "raisins", 55.0], [1670003709.795992, "peanuts", 6.0], [1670024962.3077805, "provolone", 3.0], [1670024979.5923846, "knackebrot", 3.0], [1670060986.8542209, "grapes", 45.0], [1670061001.9404771, "tomato grape", 25.0]], "2022.12.03": [[1670091844.093928, "peanuts", 2.0], [1670091851.2807515, "seaweed", 1.0], [1670091860.8195298, "cereal with milk", 1.0], [1670107931.999454, "yogurt", 1.0], [1670118430.2127497, "orzo salad", 1.0], [1670118438.8651369, "knackebrot", 3.0], [1670118449.0071752, "camembert", 5.0], [1670118459.8466823, "white chocolate", 1.0]], "2022.12.04": [[1670143299.6379852, "whiskey", 3.0], [1670156919.8399851, "chili", 0.75], [1670163400.2212129, "knackebrot", 3.0], [1670163410.1119087, "camembert", 3.0], [1670189011.5244637, "seaweed", 1.0], [1670227665.546575, "walnut pieces", 1.0], [1670227699.1997, "tomato grape", 15.0], [1670227724.214195, "rockstar recovery", 1.0]], "2022.12.05": [[1670227756.1902525, "tuna", 3.3], [1670296922.1942072, "egg salad", 5.0], [1670296946.274557, "palak paneer", 1.0], [1670296954.0020542, "banana", 1.0], [1670296961.219092, "walnut pieces", 0.5], [1670297872.4329498, "yogurt", 1.0]], "2022.12.06": [[1670316854.6369424, "pizza with cheese", 1.0], [1670381269.5493672, "feta olive mix", 1.0], [1670381280.0149958, "sausage and egg breakfast sandwich", 1.0], [1670381295.2235444, "yogurt", 1.0], [1670381305.162562, "cereal with milk", 2.0], [1670381331.8177, "protein bar", 2.0], [1670393249.260684, "whiskey", 2.0]], "2022.12.07": [[1670401451.766897, "tuna", 3.3], [1670401459.3269148, "knackebrot", 2.0], [1670465132.1927123, "orzo salad", 1.0], [1670465145.4399617, "whiskey", 2.0], [1670470350.3329282, "banana", 1.0], [1670485592.6083105, "walnut pieces", 3.0]], "2022.12.08": [[1670490040.9319117, "seaweed", 1.0], [1670490241.4670405, "protein bar", 1.0], [1670491406.6642854, "cereal with milk", 1.0], [1670538847.9128428, "knackebrot", 2.0], [1670538857.8515701, "provolone", 2.0]]}, "exercise": {"2022.10.09": [[1665358800.0, "rowing", 437.0]], "2022.10.10": [[1665418165.425741, "pushups", 25.0], [1665478264.4525938, "dancing", 150.0]], "2022.10.11": [[1665532783.2261102, "pushups", 25.0], [1665536520.7957904, "rowing", 503.0]], "2022.10.12": [[1665579632.0227497, "pushups", 50.0], [1665592490.7628436, "rowing", 522.0]], "2022.10.13": [[1665700626.5592592, "pushups", 25.0], [1665704328.400128, "rowing", 592.0]], "2022.10.14": [[1665822372.9973266, "rowing", 420.0]], "2022.10.15": [[1665863789.9637918, "pushups", 50.0], [1665865548.3751767, "rowing", 519.0]], "2022.10.16": [], "2022.10.17": [[1666098094.002423, "dancing", 120.0]], "2022.10.18": [], "2022.10.19": [[1666224012.409084, "rowing", 581.0]], "2022.10.20": [], "2022.10.21": [[1666409918.0785503, "rowing", 530.0]], "2022.10.22": [[1666490347.7767444, "rowing", 317.0]], "2022.10.23": [], "2022.10.24": [[1666660016.2096872, "pushups", 25.0], [1666686673.363021, "dancing", 150.0]], "2022.10.25": [], "2022.10.26": [[1666839273.819078, "rowing", 520.0]], "2022.10.27": [[1666923317.025998, "rowing", 500.0]], "2022.10.28": [], "2022.10.29": [], "2022.10.30": [], "2022.10.31": [], "2022.11.01": [[1667298123.9964237, "pushups", 70.0]], "2022.11.02": [[1667374673.2543023, "pushups", 45.0]], "2022.11.03": [[1667468062.7213428, "pushups", 50.0]], "2022.11.04": [[1667559913.9997046, "pushups", 45.0]], "2022.11.05": [[1667642164.1500876, "pushups", 70.0]], "2022.11.06": [[1667722040.5314326, "pushups", 75.0]], "2022.11.07": [[1667812550.7488673, "pushups", 80.0]], "2022.11.08": [[1667896496.0655248, "pushups", 60.0]], "2022.11.09": [[1667983721.0086155, "pushups", 60.0]], "2022.11.10": [[1668074630.5486083, "pushups", 60.0]], "2022.11.12": [[1668251147.8151653, "pushups", 65.0]], "2022.11.11": [[1668251228.3436189, "pushups", 30.0]], "2022.11.13": [[1668338157.1149275, "pushups", 60.0]], "2022.11.14": [[1668443821.504034, "pushups", 30.0]], "2022.11.15": [[1668530648.5000556, "pushups", 30.0]], "2022.11.16": [[1668600226.8086197, "pushups", 60.0]], "2022.11.17": [[1668825089.5916116, "rowing", 0.0]], "2022.11.18": [[1668825129.722567, "rowing", 300.0]], "2022.11.19": [[1668866967.8982434, "pushups", 60.0], [1668877546.2893662, "rowing", 1155.0]], "2022.11.20": [[1669001063.7232935, "rowing", 900.0]], "2022.11.21": [[1669051945.015859, "pushups", 30.0], [1669052756.2421446, "rowing", 600.0], [1669062209.175649, "dancing", 150.0]], "2022.11.22": [[1669141814.3013406, "pushups", 30.0]], "2022.11.29": [[1669794963.1667597, "rowing", 300.0]], "2022.11.28": [[1669766734.2294152, "dancing", 210.0]], "2022.11.27": [[1669767000.3692467, "pushups", 30.0]], "2022.11.26": [], "2022.11.25": [], "2022.11.24": [], "2022.11.23": [], "2022.11.30": [[1669864962.0805385, "rowing", 305.0], [1669871400.5774672, "pushups", 30.0]], "2022.12.01": [[1669962532.6356726, "pushups", 60.0]], "2022.12.02": [[1670003346.8894472, "pushups", 30.0]], "2022.12.03": [[1670115690.9582217, "rowing", 400.0], [1670115700.9034762, "hillhiking", 45.0]], "2022.12.04": [], "2022.12.05": [[1670296976.494963, "rowing", 300.0], [1670316712.9454865, "dancing", 75.0], [1670393220.6061513, "pushups", 30.0]], "2022.12.06": [[1670316728.661275, "rowing", 200.0]], "2022.12.07": [], "2022.12.08": []}, "accounts": {"2022.10.07": [[1665355742.0701172, "Doordash.", 19.96, 0, "Sophia"], [1665356526.0605235, "Amazon Fresh.", 109.92, 0, "Groceries"], [1665356599.3242688, "AmEx payment.", 2000.0, 0, ""]], "2022.10.09": [[1665377658.4692624, "Uber home.", 29.97, 0, "Socializing"], [1665377712.3581386, "Lyft downtown.", 34.56, 0, "Socializing"]], "2022.10.10": [[1665461999.5765674, "Google storage", 29.99, 0, "Office"], [1665527453.4288507, "Lyft to DNA Lounge.", 23.98, 0, ""], [1665527507.9910893, "ATM withdrawal at DNA Lounge.", 203.75, 200.0, "Transfer"]], "2022.10.11": [[1665508334.3577971, "Bridging funds for Sophia.", 250.0, 0, "Sophia"], [1665520815.0341976, "Helping Circadia.", 250.0, 0, "Circadia"], [1665526973.2937884, "Transfer to Paypal.", 2000.0, 2000.0, "Transfer"], [1665527399.9689617, "Uber home.", 35.96, 0, ""]], "2022.10.12": [], "2022.10.13": [], "2022.10.14": [], "2022.10.15": [], "2022.10.16": [[1665923553.540632, "TurboTax 2021 Federal Tax filing", 129.47, 0, "Taxes"]], "2022.10.17": [], "2022.10.18": [], "2022.10.19": [], "2022.10.20": [], "2022.10.21": [], "2022.10.22": [], "2022.10.23": [], "2022.10.24": [], "2022.10.25": [], "2022.10.26": [], "2022.10.27": [], "2022.10.28": [], "2022.10.29": [], "2022.10.30": [], "2022.10.31": [], "2022.11.01": [], "2022.11.02": [], "2022.11.03": [], "2022.11.04": [], "2022.11.05": [], "2022.11.06": [], "2022.11.07": [], "2022.11.08": [], "2022.11.09": [], "2022.11.10": [[1668077595.387265, "Progressive Insurance premium for Skoolie", 332.0, 0, "Vehicles"], [1668077679.8918707, "Coffee and muesli", 8.1, 0, "Restaurant"], [1668077725.8930347, "ALDI", 8.33, 0, "Groceries"]], "2022.11.12": [], "2022.11.11": [], "2022.11.13": [], "2022.11.14": [], "2022.11.15": [[1668532632.8621974, "LicenseXpress registration renewal Yaris", 85.75, 0, "Vehicles"], [1668532688.2119627, "AmEx payment (making room for tax payment)", 13283.44, 0, "Credit Card"]], "2022.11.16": [], "2022.11.17": [], "2022.11.18": [], "2022.11.19": [[1668920805.4859786, "hair product", 32.58, 0, "Groceries"], [1668921811.6055846, "hair product", 39.82, 0, "Groceries"]], "2022.11.20": [], "2022.11.21": [[1669038931.9996595, "Fee to credit card processor for IRS payment", 234.14, 0, "Taxes"], [1669038965.2710145, "2021 Federal Tax payment", 12521.0, 0, "Taxes"]], "2022.11.22": [], "2022.11.29": [], "2022.11.28": [], "2022.11.27": [], "2022.11.26": [], "2022.11.25": [], "2022.11.24": [], "2022.11.23": [], "2022.11.30": [], "2022.12.01": [], "2022.12.02": [], "2022.12.03": [], "2022.12.04": [], "2022.12.05": [], "2022.12.06": [], "2022.12.07": [], "2022.12.08": []}, "cache": {"caloriethreshold": 1750, "caloriestotal": 104100, "dayscaloriesunknown": 6}, "milestones": {"2022.10.16": [["20221016044035.1", "VOXA-MODULARIZED-ALPHA", 57], ["20221016044853.1", "2021-TAXES-DONE", 8], ["20221016045411.1", "CFF-CSO-ORGANIZED", 14], ["20200405215038.1", "CC-RESEARCH-START", 14], ["20210214032919.1", "METRICS-MERGED", 7]], "2022.10.17": [], "2022.10.18": [], "2022.10.19": [], "2022.10.20": [], "2022.10.21": [], "2022.10.22": [], "2022.10.23": [], "2022.10.24": [], "2022.10.25": [], "2022.10.26": [], "2022.10.27": [], "2022.10.28": [], "2022.10.29": [], "2022.10.30": [], "2022.10.31": [], "2022.11.01": [], "2022.11.02": [], "2022.11.03": [], "2022.11.04": [], "2022.11.05": [], "2022.11.06": [], "2022.11.07": [], "2022.11.08": [], "2022.11.09": [], "2022.11.10": [], "2022.11.12": [], "2022.11.11": [], "2022.11.13": [], "2022.11.14": [], "2022.11.15": [], "2022.11.16": [], "2022.11.17": [], "2022.11.18": [], "2022.11.19": [], "2022.11.20": [], "2022.11.21": [], "2022.11.22": [], "2022.11.29": [], "2022.11.28": [], "2022.11.27": [], "2022.11.26": [], "2022.11.25": [], "2022.11.24": [], "2022.11.23": [], "2022.11.30": [], "2022.12.01": [], "2022.12.02": [], "2022.12.03": [], "2022.12.04": [], "2022.12.05": [], "2022.12.06": [], "2022.12.07": [], "2022.12.08": []}}